Workbook

Sheet DASHBOARD
A1: MOLINAS DATABASE DASHBOARD
A2: Executive view — Stakeholder, Regulatory, Policy & News Intelligence
A4: STAKEHOLDER | D4: P1 GATEKEEPER | E4: P2 SCALE ENABLER | F4: P3 SUPPORT | G4: REGULATORY ITEMS | J4: POLICY AREAS | M4: NEWS
A5: =COUNTA('MoLINas Integrated Plan'!B6:B37) -> 32 | D5: =COUNTIF('MoLINas Integrated Plan'!I6:I37,"P1") -> 14 | E5: =COUNTIF('MoLINas Integrated Plan'!I6:I37,"P2") -> 17 | F5: =COUNTIF('MoLINas Integrated Plan'!I6:I37,"P3") -> 1 | G5: =COUNTA('DASAR STAKEHOLDER & REGULASI'!A2:A215) -> 32 | J5: =COUNTA('USULAN & PERBANDINGAN'!A2:A13) -> 12 | M5: =COUNTA('DATABASE BERITA'!A2:A300) -> 130
A8: STAKEHOLDER LANDSCAPE | G8: POLICY & REGULATORY | K8: NEWS INTELLIGENCE
A9: Priority | B9: Jumlah | D9: Work Package | E9: Jumlah | G9: Indicator | H9: Value | K9: Segmen | L9: Jumlah | M9: Coverage | N9: Value
A10: P1 | B10: =COUNTIF('MoLINas Integrated Plan'!I6:I37,A10) -> 14 | D10: Hulu | E10: =COUNTIF('MoLINas Integrated Plan'!J6:J37,"*"&D10&"*") -> 11 | G10: Stakeholder / lembaga | H10: =COUNTA('DASAR STAKEHOLDER & REGULASI'!A2:A150) -> 32 | K10: Global | L10: =COUNTIF('DATABASE BERITA'!K:K,DASHBOARD!K10) -> 42 | M10: Countries | N10: =SUMPRODUCT(('DATABASE BERITA'!C2:C131<>"")/COUNTIF('DATABASE BERITA'!C2:C131,'DATABASE BERITA'!C2:C131&"")) -> 11
A11: P2 | B11: =COUNTIF('MoLINas Integrated Plan'!I6:I37,A11) -> 17 | D11: Midstream | E11: =COUNTIF('MoLINas Integrated Plan'!J6:J37,"*"&D11&"*") -> 4 | G11: Regulatory items | H11: =COUNTA('DASAR STAKEHOLDER & REGULASI'!B2:B150) -> 39 | K11: Lokal | L11: =COUNTIF('DATABASE BERITA'!K:K,DASHBOARD!K11) -> 31 | M11: Themes | N11: =SUMPRODUCT(('DATABASE BERITA'!F2:F131<>"")/COUNTIF('DATABASE BERITA'!F2:F131,'DATABASE BERITA'!F2:F131&"")) -> 23
A12: P3 | B12: =COUNTIF('MoLINas Integrated Plan'!I6:I37,A12) -> 1 | D12: Hilir | E12: =COUNTIF('MoLINas Integrated Plan'!J6:J37,"*"&D12&"*") -> 7 | G12: Policy areas | H12: =COUNTA('USULAN & PERBANDINGAN'!A2:A100) -> 12 | K12: Molinas | L12: =COUNTIF('DATABASE BERITA'!K:K,DASHBOARD!K12) -> 57 | M12: Latest | N12: =MAX('DATABASE BERITA'!B:B) -> 46274
D13: Enablers | E13: =COUNTIF('MoLINas Integrated Plan'!J6:J37,"*"&D13&"*") -> 10
A28: MOLINAS STRATEGIC AREAS — POLICY / ECOSYSTEM
A29: Area | E29: Key Direction | J29: R&D Priority
A30: ='USULAN & PERBANDINGAN'!B2 -> Mineral & Bahan Baku | E30: ='USULAN & PERBANDINGAN'!F2 -> Memperluas ekosistem KBLBB sampai upstream bahan baku strategis. Mengintegrasikan roadmap mineral kritis dengan baterai, hilirisasi, traceability, ketahanan pasok, efisiensi penggunaan material dan pengembangan material substitusi. | J30: ='USULAN & PERBANDINGAN'!H2 -> 10% dari total portofolio R&D KBLBB diarahkan pada refining, material baterai, precursor, material aktif, efisiensi material dan substitusi mineral kritis.
A31: ='USULAN & PERBANDINGAN'!B3 -> Baterai & Teknologi Baterai | E31: ='USULAN & PERBANDINGAN'!F3 -> Mengubah pendekatan dari battery component menjadi battery lifecycle ecosystem. Mencakup cell, module/pack, BMS, thermal management, safety, diagnostics/SOH, second-life, collection, recycling, recovery, traceability dan battery passport. | J31: ='USULAN & PERBANDINGAN'!H3 -> 20% dari portofolio R&D KBLBB untuk battery safety, fast charging, SOH/diagnostics, thermal management, LFP/NMC dan chemistry alternatif, second-life, recycling dan battery passport.
A32: ='USULAN & PERBANDINGAN'!B4 -> Powertrain & Komponen Elektrikal | E32: ='USULAN & PERBANDINGAN'!F4 -> Memperdalam lokalisasi teknologi inti powertrain, termasuk motor, inverter/controller, BMS, charger, power electronics dan komponen kritis; disertai supplier development dan transfer teknologi. | J32: ='USULAN & PERBANDINGAN'!H4 -> 20% untuk motor listrik, inverter/controller, semiconductor/power electronics, thermal management, control system dan system efficiency.
A33: ='USULAN & PERBANDINGAN'!B5 -> Chassis / Rangka & Komponen Kendaraan | E33: ='USULAN & PERBANDINGAN'!F5 -> Memperkuat domestic engineering & supplier capability untuk frame, suspension, steering, braking, wheel, body dan safety component. | J33: ='USULAN & PERBANDINGAN'!H5 -> 5% untuk lightweighting, structural engineering, crashworthiness, durability dan advanced material.
A34: ='USULAN & PERBANDINGAN'!B6 -> Manufaktur & Perakitan | E34: ='USULAN & PERBANDINGAN'!F6 -> Menjadikan fase CBU sebagai transisi menuju pendalaman manufaktur domestik. Dukungan dikaitkan dengan investasi, produksi, TKDN, supplier localization, transfer teknologi, tenaga kerja, R&D dan ekspor. | J34: ='USULAN & PERBANDINGAN'!H6 -> 15% untuk design engineering, process engineering, automation, quality system, manufacturing technology dan production digitalization.
A35: ='USULAN & PERBANDINGAN'!B7 -> Sertifikasi & Keselamatan Kendaraan | E35: ='USULAN & PERBANDINGAN'!F7 -> Memperluas assurance framework untuk EV dan software-defined vehicle, termasuk battery safety, functional safety, cybersecurity, OTA/software validation, SOH dan digital vehicle record. | J35: ='USULAN & PERBANDINGAN'!H7 -> 8% untuk testing/certification technology, battery safety, functional safety, cybersecurity, software validation dan interoperability.
A36: ='USULAN & PERBANDINGAN'!B8 -> Infrastruktur Pengisian & Ketenagalistrikan | E36: ='USULAN & PERBANDINGAN'!F8 -> Mengubah charging infrastructure menjadi integrated charging ecosystem: interoperability, roaming/payment, fast & ultrafast charging, load management, smart charging, renewable integration dan V2G. | J36: ='USULAN & PERBANDINGAN'!H8 -> 7% untuk smart charging, load management, V2G, grid integration, renewable-powered charging dan charging interoperability.
A37: ='USULAN & PERBANDINGAN'!B9 -> Konektivitas & Digital | E37: ='USULAN & PERBANDINGAN'!F9 -> Menambahkan digital/connected vehicle sebagai bagian formal ekosistem KBLBB, meliputi TCU/IoT, GPS/4G/5G, vehicle data, cybersecurity, OTA, digital vehicle record dan koneksi dengan battery passport. | J37: ='USULAN & PERBANDINGAN'!H9 -> 5% untuk vehicle data architecture, cybersecurity, OTA, telematics, AI/analytics dan digital records.
A38: ='USULAN & PERBANDINGAN'!B10 -> Fiskal, Perdagangan & Pembiayaan | E38: ='USULAN & PERBANDINGAN'!F10 -> Membentuk performance-based incentive framework: dukungan dikaitkan dengan TKDN, investasi, produksi, supplier lokal, tenaga kerja, R&D, ekspor dan kontribusi emisi; termasuk milestone, monitoring dan exit strategy. | J38: ='USULAN & PERBANDINGAN'!H10 -> 7% untuk matching fund, applied R&D, technology adoption, commercialization dan industrial research.
A39: ='USULAN & PERBANDINGAN'!B11 -> Lingkungan & Ekonomi Sirkular | E39: ='USULAN & PERBANDINGAN'!F11 -> Membangun battery circular economy framework, termasuk producer responsibility, collection, traceability, diagnosis, safe dismantling, second-life, recycling, recovery dan material recovery. | J39: ='USULAN & PERBANDINGAN'!H11 -> 3% untuk second-life, recycling efficiency, safe dismantling, material recovery dan circular design.
A40: ='USULAN & PERBANDINGAN'!B12 -> Pertahanan & Strategic Use Case | E40: ='USULAN & PERBANDINGAN'!F12 -> Membuka strategic/institutional pathway dalam ekosistem KBLBB, termasuk procurement, spesifikasi khusus, security requirement, lifecycle support dan keterlibatan industri strategis. | J40: ='USULAN & PERBANDINGAN'!H12 -> 3% untuk ruggedized EV, mission-specific battery/powertrain, secure communication, energy resilience dan defense-grade testing.
A41: ='USULAN & PERBANDINGAN'!B13 -> Program Strategis Nasional & Kelembagaan Lintas Sektor | E41: ='USULAN & PERBANDINGAN'!F13 -> Membangun National EV Ecosystem Governance: single data, KPI dashboard, roadmap lintas K/L, funding alignment, monitoring-evaluation dan periodic policy review. | J41: ='USULAN & PERBANDINGAN'!H13 -> 10% untuk national R&D portfolio, shared testing facility, technology readiness monitoring dan integrasi riset lintas kategori.
A44: LATEST NEWS — LINKED TO DATABASE BERITA
A45: Tanggal | B45: Negara | C45: Perusahaan / Brand | D45: Pilar Ekosistem | E45: Status | F45: Tema | G45: Media
A46: =IFERROR('DATABASE BERITA'!B2,"") -> 46274 | B46: =IFERROR('DATABASE BERITA'!C2,"") -> Indonesia | C46: =IFERROR('DATABASE BERITA'!D2,"") -> BKPM / Pemerintah | D46: =IFERROR('DATABASE BERITA'!E2,"") -> ENABLERS | E46: =IFERROR('DATABASE BERITA'!K2,"") -> Lokal | F46: =IFERROR('DATABASE BERITA'!F2,"") -> Charging / Swapping | G46: =IFERROR('DATABASE BERITA'!I2,"") -> ANTARA
A47: =IFERROR('DATABASE BERITA'!B3,"") -> 46273 | B47: =IFERROR('DATABASE BERITA'!C3,"") -> Indonesia | C47: =IFERROR('DATABASE BERITA'!D3,"") -> IBC / CATL | D47: =IFERROR('DATABASE BERITA'!E3,"") -> VALUE CHAIN (HULU–MIDSTREAM–HILIR) | E47: =IFERROR('DATABASE BERITA'!K3,"") -> MoLiNas | F47: =IFERROR('DATABASE BERITA'!F3,"") -> HULU — Battery & Components | G47: =IFERROR('DATABASE BERITA'!I3,"") -> Bisnis.com
A48: =IFERROR('DATABASE BERITA'!B4,"") -> 46270 | B48: =IFERROR('DATABASE BERITA'!C4,"") -> Indonesia | C48: =IFERROR('DATABASE BERITA'!D4,"") -> Pemerintah / MoLiNas | D48: =IFERROR('DATABASE BERITA'!E4,"") -> REGULATORY & POLICY | E48: =IFERROR('DATABASE BERITA'!K4,"") -> MoLiNas | F48: =IFERROR('DATABASE BERITA'!F4,"") -> Regulasi, Kebijakan & Insentif | G48: =IFERROR('DATABASE BERITA'!I4,"") -> ITERA
A49: =IFERROR('DATABASE BERITA'!B5,"") -> 46270 | B49: =IFERROR('DATABASE BERITA'!C5,"") -> Indonesia | C49: =IFERROR('DATABASE BERITA'!D5,"") -> DPR RI / BYD | D49: =IFERROR('DATABASE BERITA'!E5,"") -> REGULATORY & POLICY | E49: =IFERROR('DATABASE BERITA'!K5,"") -> Lokal | F49: =IFERROR('DATABASE BERITA'!F5,"") -> TKDN & Sertifikasi | G49: =IFERROR('DATABASE BERITA'!I5,"") -> DPR RI
A50: =IFERROR('DATABASE BERITA'!B6,"") -> 46270 | B50: =IFERROR('DATABASE BERITA'!C6,"") -> Indonesia | C50: =IFERROR('DATABASE BERITA'!D6,"") -> BYD | D50: =IFERROR('DATABASE BERITA'!E6,"") -> REGULATORY & POLICY | E50: =IFERROR('DATABASE BERITA'!K6,"") -> Lokal | F50: =IFERROR('DATABASE BERITA'!F6,"") -> TKDN & Sertifikasi | G50: =IFERROR('DATABASE BERITA'!I6,"") -> OtoDream

Sheet MoLINas Integrated Plan
A1: MOLINAS – INTEGRATED STAKEHOLDER, REGULATORY, PIC & GANTT SCHEDULE
AB2: PHASE 0 (2026) Penetrasi Pasar & Penetapan Komponen Utama | AP2: STATUS STAKEHOLDER
A3: STAKEHOLDER & REGULATORY | Q3: ENGAGEMENT & GOVERNANCE | AB3: WEEKLY GANTT – 2026
Y4: AUGUST 2026 | Z4: SEPTEMBER 2026 | AD4: OCTOBER 2026 | AH4: NOVEMBER 2026 | AL4: DECEMBER 2026 | AP4: STATUS | AQ4: Engagement Status | AR4: Last Engagement / Update | AS4: Follow-Up / Commitment | AT4: Relationship Status
A5: No | B5: Stakeholder / Lembaga | C5: Kategori / Isu Utama | D5: Criticality (1–5) | E5: Breadth of Impact (1–5) | F5: Dependency (1–5) | G5: Urgency (1–5) | H5: Weighted Score | I5: Prioritas | J5: Domain Ekosistem | K5: Isu | L5: Contoh Regulasi Utama / Dasar | M5: Ruang Lingkup | N5: Terkait Tahap Ekosistem | O5: Ecosystem Value Chain Layer | P5: Cross-Cutting Enabler | Q5: Agenda Engagement | R5: Lead PIC (WS) | S5: Supporting PIC | T5: BOD Accountable | U5: PD/PMO | V5: Peran Danantara | W5: ALVA / Mitra | X5: Target Outcome | Y5: Agt W1 | Z5: Sep W1 | AA5: Sep W2 | AB5: Sep W3 | AC5: Sep W4 | AD5: Okt W1 | AE5: Okt W2 | AF5: Okt W3 | AG5: Okt W4 | AH5: Nov W1 | AI5: Nov W2 | AJ5: Nov W3 | AK5: Nov W4 | AL5: Des W1 | AM5: Des W2 | AN5: Des W3 | AO5: Des W4
A6: 1 | B6: BRIN (Connector Charger) | C6: R&D / technology development | D6: 5 | E6: 4 | F6: 4 | G6: 4 | H6: =(D6*$B$56)+(E6*$B$57)+(F6*$B$58)+(G6*$B$59) -> 4.3 | I6: =IF(H6>=4.25,"P1",IF(H6>=3,"P2","P3")) -> P1 | J6: Midstream | K6: Baterai & Teknologi Baterai; Powertrain & Komponen Elektrikal | L6: SNI baterai & keselamatan; SNI komponen kelistrikan | M6: Riset, pengembangan, validasi teknologi baterai, motor listrik, controller, inverter, BMS dan komponen | N6: Bahan Baku & Komponen Dasar; Infrastruktur & Pendukung | O6: 1. Engineering, Technology & R&D; 2. Raw Materials & Components; 7. Infrastructure & Charging | P6: Technology, Data & Digital | Q6: R&D / technology development | R6: WS3 – Innovation | S6: WS2 Ecosystem; WS2 Legal | T6: CTO | U6: Monitoring | V6: Support | W6: Technical partner | X6: Technology validation & collaboration | Z6: Audiensi | AA6: Audiensi | AB6: Riset & kolaborasi teknologi | AC6: Riset & kolaborasi teknologi | AD6: Scope alignment | AE6: Validasi teknologi | AF6: Validasi teknologi | AG6: Validasi teknologi | AH6: Dukungan pengembangan | AI6: Dukungan pengembangan | AJ6: Dukungan pengembangan | AK6: Dukungan pengembangan | AL6: Monitoring | AM6: Monitoring | AN6: Monitoring | AO6: Monitoring | AP6: In Progress | AQ6: Ongoing | AR6: 46289 | AS6: Continue technical discussion on connector, charging interface, research results, standardization direction and potential application in MOLINAS. | AT6: Active
A7: 2 | B7: IBC | C7: Teknologi & Baterai | D7: 5 | E7: 5 | F7: 5 | G7: 4 | H7: =(D7*$B$56)+(E7*$B$57)+(F7*$B$58)+(G7*$B$59) -> 4.75 | I7: =IF(H7>=4.25,"P1",IF(H7>=3,"P2","P3")) -> P1 | J7: Hulu | K7: Battery Cell | M7: Produksi battery cell domestik, kapasitas manufaktur, yield, quality, local input, dan keterhubungan dengan OEM | N7: Manufaktur & Supply Chain ; Bahan Baku & Komponen Dasar | O7: 2. Raw Materials & Components; 3. Manufacturing & Assembly; 4. Supply Chain & Logistics | Q7: Cell manufacturing / industrialization & ecosystem integration | R7: WS2 – Ecosystem | S7: WS3 – Innovation, Supply Chain | T7: CMO | U7: Monitoring | V7: Support | W7: Partner input | X7: Kesiapan dan scale-up produksi battery cell domestik serta integrasi dengan OEM | Z7: Audiensi / engagement awal | AA7: Audiensi / engagement awal | AB7: Pembahasan kebutuhan produk & OEM | AC7: Diskusi awal | AD7: Alignment deployment | AE7: Koordinasi uji coba | AF7: Koordinasi uji coba | AG7: Koordinasi uji coba | AH7: Koordinasi implementasi fleet/deployment | AI7: Koordinasi implementasi fleet/deployment | AJ7: Koordinasi implementasi fleet/deployment | AK7: Koordinasi implementasi fleet/deployment | AL7: Monitoring | AM7: Monitoring | AN7: Monitoring | AO7: Monitoring | AP7: In Progress | AQ7: Ongoing | AR7: 46289 | AS7: Continue battery standardization and alignment on battery specifications, supply readiness and OEM integration. | AT7: Active
A8: 3 | B8: ALVA (Mitra / OEM) | C8: OEM collaboration | D8: 4 | E8: 5 | F8: 5 | G8: 4 | H8: =(D8*$B$56)+(E8*$B$57)+(F8*$B$58)+(G8*$B$59) -> 4.45 | I8: =IF(H8>=4.25,"P1",IF(H8>=3,"P2","P3")) -> P1 | J8: Hulu | K8: Mitra / OEM | L8: Ketentuan industri/manufaktur dan partnership yang relevan | M8: OEM collaboration, partnership structure, technical/commercial input | N8: Manufaktur & Supply Chain; Distribusi & Pasar | O8: 3. Manufacturing & Assembly; 4. Supply Chain & Logistics; 5. Sales, Distribution & Market | Q8: OEM collaboration | R8: WS1 – Business Development | S8: WS3 Marketing, Supply Chain; WS4 Finance, WS2 Ecosystem | T8: CMO | U8: Monitoring | V8: Accompany | W8: Partner / OEM | X8: Partnership structure & commitment | Z8: Audiensi / engagement awal | AA8: Audiensi / engagement awal | AB8: Pembahasan kebutuhan produk & OEM | AC8: Alignment kebutuhan fleet / armada | AD8: Alignment kebutuhan fleet / armada | AE8: Alignment komersial & deployment | AF8: Koordinasi uji coba | AG8: Koordinasi uji coba | AH8: Koordinasi implementasi fleet | AI8: Koordinasi implementasi fleet | AJ8: Koordinasi deployment | AK8: Koordinasi deployment | AL8: Monitoring engagement | AM8: Monitoring engagement | AN8: Monitoring engagement | AO8: Monitoring engagement | AP8: In Progress | AQ8: Ongoing | AR8: 46289 | AS8: Continue OEM/product discussion, including technical specifications, production readiness, market segmentation and partnership alignment. | AT8: Active
A9: 4 | B9: GESITS (Mitra / OEM) | C9: OEM collaboration | D9: 4 | E9: 5 | F9: 5 | G9: 4 | H9: =(D9*$B$56)+(E9*$B$57)+(F9*$B$58)+(G9*$B$59) -> 4.45 | I9: =IF(H9>=4.25,"P1",IF(H9>=3,"P2","P3")) -> P1 | J9: Hulu | K9: Mitra / OEM | L9: Ketentuan industri/manufaktur dan partnership yang relevan | M9: OEM collaboration, partnership structure, technical/commercial input | N9: Manufaktur & Supply Chain; Distribusi & Pasar | O9: 3. Manufacturing & Assembly; 4. Supply Chain & Logistics; 5. Sales, Distribution & Market | Q9: OEM collaboration | R9: WS1 – Business Development | S9: WS3 Marketing, Supply Chain; WS4 Finance, WS2 Ecosystem | T9: CMO | U9: Monitoring | V9: Accompany | W9: Partner / OEM | X9: Partnership structure & commitment | Y9: Partner / OEM mapping | Z9: Audiensi / engagement awal | AA9: Audiensi / engagement awal | AB9: Pembahasan kebutuhan produk & OEM | AC9: Alignment kebutuhan fleet / armada | AD9: Alignment kebutuhan fleet / armada | AE9: Alignment komersial & deployment | AF9: Koordinasi uji coba | AG9: Koordinasi uji coba | AH9: Koordinasi implementasi fleet | AI9: Koordinasi implementasi fleet | AJ9: Koordinasi deployment | AK9: Koordinasi deployment | AL9: Monitoring engagement | AM9: Monitoring engagement | AN9: Monitoring engagement | AO9: Monitoring engagement | AP9: In Progress | AQ9: Ongoing | AR9: 46289 | AS9: Continue OEM/product discussion, including technical specifications, production readiness, battery/brick alignment and partnership alignment. | AT9: Active
A10: 5 | B10: GESITS (Teknologi) | C10: Teknologi & Baterai | D10: 5 | E10: 4 | F10: 4 | G10: 4 | H10: =(D10*$B$56)+(E10*$B$57)+(F10*$B$58)+(G10*$B$59) -> 4.3 | I10: =IF(H10>=4.25,"P1",IF(H10>=3,"P2","P3")) -> P1 | J10: Hulu | K10: Baterai & Teknologi Baterai | M10: BRICK - jenis baterai yang dikembangkan/dimiliki GESITS | N10: Bahan Baku & Komponen Dasar; | O10: 1. Engineering, Technology & R&D; 2. Raw Materials & Components | P10: Technology, Data & Digital | Q10: Standardisasi tipe baterai | R10: WS3 – Innovation | S10: WS2 Ecosystem; WS4 Finance | T10: CTO | U10: Monitoring | V10: Co-Lead | W10: Partner input | X10: Alignment dan integrasi teknologi BRICK dalam ekosistem baterai MoLiNas | Z10: Stakeholder engagement | AA10: Regulatory alignment | AB10: Regulatory alignment | AC10: Regulatory alignment | AD10: Ecosystem coordination | AE10: Ecosystem coordination | AF10: Ecosystem coordination | AG10: Ecosystem coordination | AH10: Partnership / deployment pathway | AI10: Partnership / deployment pathway | AJ10: Partnership / deployment pathway | AK10: Partnership / deployment pathway | AL10: Monitoring | AM10: Monitoring | AN10: Monitoring | AO10: Monitoring | AP10: In Progress | AQ10: Ongoing | AR10: 46289 | AS10: Continue battery standardization discussion and alignment of GESITS battery technology/BRICK with MOLINAS requirements. | AT10: Active
A11: 6 | B11: Kemenperin | C11: 1. Regulatory, TKDN, industrial regulation 2. OEM, manufaktur & supply chain | D11: 5 | E11: 5 | F11: 5 | G11: 5 | H11: =(D11*$B$56)+(E11*$B$57)+(F11*$B$58)+(G11*$B$59) -> 5 | I11: =IF(H11>=4.25,"P1",IF(H11>=3,"P2","P3")) -> P1 | J11: Hulu | K11: 1. Baterai & Teknologi Baterai 2. Powertrain & Komponen Elektrikal; Manufaktur & Perakitan | L11: 1. Permenperin No. 28/2023 (TKDN KLBB); Permenperin No. 35/2025 (Sertifikasi TKDN & BMP); SNI baterai & keselamatan; Regulasi lembaga penilai (Permen LHK No. 9/2024) 2. Permenperin No. 28/2023; Permenperin No. 35/2023; SNI komponen kelistrikan; Permenperin No. 29/2023 (Industri KBLBB); Permenperin No. 35/2023; Permenperin No. 38/2023 | M11: 1. Produksi/impor baterai, TKDN, standardisasi (SNI), keselamatan, pengelolaan baterai bekas, riset & pengembangan teknologi 2. Motor listrik, controller, inverter, BMS, komponen utama/pendukung; industri kendaraan listrik, perakitan OEM/IKD/CKD, TKDN, sertifikasi industri, fasilitas produksi | N11: Bahan Baku & Komponen Dasar; Manufaktur & Supply Chain; Daur Ulang & Ekosistem Sirkular | O11: 1. Engineering, Technology & R&D; 2. Raw Materials & Components; 3. Manufacturing & Assembly; 4. Supply Chain & Logistics; 9. Circular Economy & Recycling | P11: Policy, Regulation & Standards; Technology, Data & Digital | Q11: 1. Regulatory, TKDN, industrial regulation 2. OEM, manufaktur & supply chain | R11: WS2 – Legal | S11: 1. WS2 Ecosystem; WS3 Innovation, Supply Chain 2. WS3 Supply Chain, Innovation; WS2 Legal | T11: 1. CTO 2. COO | U11: Monitoring | V11: 1. Accompany / Co-Lead 2. Accompany | W11: 1. Technical input 2. OEM/industry input | X11: 1. Regulatory pathway & TKDN clear 2. Production & industrialization roadmap | Z11: Audiensi awal | AA11: Audiensi awal | AB11: Pembahasan regulasi & TKDN | AC11: Pembahasan regulasi & TKDN | AD11: Alignment akhir | AE11: Finalisasi TKDN & manufaktur | AF11: Finalisasi TKDN & manufaktur | AG11: Finalisasi TKDN & manufaktur | AH11: Implementasi & monitoring | AI11: Implementasi & monitoring | AJ11: Implementasi & monitoring | AK11: Implementasi & monitoring | AL11: Monitoring | AM11: Monitoring | AN11: Monitoring | AO11: Monitoring | AP11: In Progress | AQ11: Planned | AS11: Map and schedule engagement with Kemenperin to discuss regulatory pathway, TKDN, industrial regulation, OEM, manufacturing and supply-chain readiness. | AT11: Need Follow Up
A12: 7 | B12: Kemenhub | C12: Uji tipe, SUT, SRUT, kelaikan | D12: 5 | E12: 4 | F12: 5 | G12: 5 | H12: =(D12*$B$56)+(E12*$B$57)+(F12*$B$58)+(G12*$B$59) -> 4.8 | I12: =IF(H12>=4.25,"P1",IF(H12>=3,"P2","P3")) -> P1 | J12: Hulu | K12: Sertifikasi Kendaraan (Uji Tipe, SUT, SRUT); Chassis/Rangka & Komponen Kendaraan | L12: Permenhub No. 87/2020 (Uji Tipe KLBB); Permenhub No. 44/2020 jo. 86/2020 (Pengujian tipe kendaraan listrik); Ketentuan SUT & SRUT; Permenperin No. 28/2023; Ketentuan keselamatan kendaraan (Kemenhub) | M12: Uji tipe, homologasi, SUT (TIPE), SRUT (produksi), registrasi, keselamatan & kelaikan jalan; rangka, suspensi, rem, roda, body, keselamatan & kelaikan teknis | N12: Manufaktur & Supply Chain; Distribusi & Pasar; Pengguna & Layanan | O12: 2. Raw Materials & Components; 3. Manufacturing & Assembly; 4. Supply Chain & Logistics; 5. Sales, Distribution & Market; 6. User, Service & After-Sales | P12: Policy, Regulation & Standards | Q12: Uji tipe, SUT, SRUT, kelaikan | R12: WS2 – Legal | S12: WS3 Innovation; WS2 Ecosystem | T12: CTO | U12: Monitoring | V12: Accompany | W12: Vehicle/OEM support | X12: Certification pathway (type approval) | Z12: Audiensi awal | AA12: Audiensi awal | AB12: Uji tipe, SUT, SRUT | AC12: Uji tipe, SUT, SRUT | AD12: Alignment persyaratan | AE12: Finalisasi regulasi & standar teknis | AF12: Finalisasi regulasi & standar teknis | AG12: Finalisasi regulasi & standar teknis | AH12: Sertifikasi & compliance | AI12: Sertifikasi & compliance | AJ12: Sertifikasi & compliance | AK12: Sertifikasi & compliance | AL12: Monitoring | AM12: Monitoring | AN12: Monitoring | AO12: Monitoring | AP12: Pending | AQ12: Planned | AS12: Schedule engagement to clarify type approval, SUT, SRUT and vehicle roadworthiness pathway. | AT12: Need Follow Up
A13: 8 | B13: Kemenkeu | C13: Fiskal & insentif KLBB | D13: 5 | E13: 4 | F13: 4 | G13: 4 | H13: =(D13*$B$56)+(E13*$B$57)+(F13*$B$58)+(G13*$B$59) -> 4.3 | I13: =IF(H13>=4.25,"P1",IF(H13>=3,"P2","P3")) -> P1 | J13: Enablers (Financing & Support) | K13: Fiskal, Perdagangan & Pembiayaan | L13: PMK insentif KBLBB (PPN, PPnBM, bea masuk, dll); Ketentuan perdagangan/impor-ekspor; POJK pembiayaan & leasing | M13: Insentif fiskal, bea masuk, perdagangan, pembiayaan konsumen & fleet, skema leasing, green financing | N13: Distribusi & Pasar; Pengguna & Layanan | O13: 5. Sales, Distribution & Market; 6. User, Service & After-Sales; 8. Financing & Investment | Q13: Fiskal & insentif KLBB | R13: WS4 – Finance | S13: WS2 Legal; WS1 Business Development | T13: CFO | U13: Monitoring | V13: Co-Lead | W13: - | X13: Fiscal / incentive framework clarity | Z13: Diskusi insentif & skema fiskal | AA13: Diskusi insentif & skema fiskal | AB13: Diskusi insentif & skema fiskal | AC13: Diskusi insentif & skema fiskal | AD13: Penyelarasan skema | AE13: Finalisasi skema | AF13: Finalisasi skema | AG13: Finalisasi skema | AH13: Implementasi insentif | AI13: Implementasi insentif | AJ13: Implementasi insentif | AK13: Implementasi insentif | AL13: Evaluasi | AM13: Evaluasi | AN13: Evaluasi | AO13: Evaluasi | AP13: In Progress | AQ13: Completed | AR13: 46280 | AS13: Continue follow-up on fiscal/incentive framework and inputs from the Kemenkeu FGD. | AT13: Need Follow Up
A14: 9 | B14: Bappenas (Pihak terkait: KPPII) | C14: Perencanaan nasional / PSN | D14: 5 | E14: 4 | F14: 4 | G14: 4 | H14: =(D14*$B$56)+(E14*$B$57)+(F14*$B$58)+(G14*$B$59) -> 4.3 | I14: =IF(H14>=4.25,"P1",IF(H14>=3,"P2","P3")) -> P1 | J14: Hulu | K14: Program Strategis Nasional (PSN) & Kelembagaan Lintas Sektor | L14: PP No. 42/2021 (PSN); Permenko Perekonomian No. 20/2025 (Rencana & evaluasi PSN); Regulasi terkait penugasan BUMN | M14: Koordinasi lintas K/L, penetapan/status PSN, sinkronisasi program, pendanaan, monitoring & evaluasi | N14: Semua Tahap (Ekosistem) | O14: Perlu validasi | P14: Governance & Institutional Support | Q14: Strategic program / PSN | R14: WS1 – Business Development | S14: WS1 Corporate Strategic Planning; WS2 Legal/Ecosystem; WS4 Finance | T14: CEO / CMO | U14: Monitoring | V14: Co-Lead | W14: - | X14: National program alignment & support framework | Z14: Audiensi & strategic alignment | AA14: Audiensi & strategic alignment | AB14: Audiensi & strategic alignment | AC14: Dukungan program nasional | AD14: Framework dukungan | AE14: Framework dukungan | AF14: Framework dukungan | AG14: Framework dukungan | AH14: Koordinasi implementasi | AI14: Koordinasi implementasi | AJ14: Koordinasi implementasi | AK14: Koordinasi implementasi | AL14: Monitoring | AM14: Monitoring | AN14: Monitoring | AO14: Monitoring | AP14: In Progress | AQ14: Completed | AR14: 46265 | AS14: Follow up strategic program / PSN alignment and support framework. | AT14: Need Follow Up
A15: 10 | B15: ESDM | C15: Mineral & hilirisasi | D15: 5 | E15: 4 | F15: 5 | G15: 4 | H15: =(D15*$B$56)+(E15*$B$57)+(F15*$B$58)+(G15*$B$59) -> 4.55 | I15: =IF(H15>=4.25,"P1",IF(H15>=3,"P2","P3")) -> P1 | J15: Hulu | K15: Mineral & Bahan Baku | L15: UU No. 3/2020 (Mineral dan Batubara); PP No. 25/2024 (Perubahan atas PP 96/2021); Peraturan turunannya (RKAB, hilirisasi, dll) | M15: Pasokan mineral kritis (nikel, kobalt, mangan, lithium), hilirisasi, perizinan tambang, rantai pasok bahan baku | N15: Bahan Baku & Komponen Dasar | O15: 2. Raw Materials & Components | Q15: Mineral & hilirisasi | R15: WS2 – Ecosystem | S15: WS2 Legal; WS3 Supply Chain, Innovation | T15: CTO | U15: Monitoring | V15: Accompany | W15: - | X15: Mineral supply & hilirisasi alignment | Z15: Mineral & hilirisasi (baterai) | AA15: Mineral & hilirisasi (baterai) | AB15: Mineral & hilirisasi (baterai) | AC15: Supply chain alignment | AD15: Kepastian pasokan & rantai pasok | AE15: Kepastian pasokan & rantai pasok | AF15: Kepastian pasokan & rantai pasok | AG15: Kepastian pasokan & rantai pasok | AH15: Implementasi rantai pasok | AI15: Implementasi rantai pasok | AJ15: Implementasi rantai pasok | AK15: Implementasi rantai pasok | AL15: Monitoring | AM15: Monitoring | AN15: Monitoring | AO15: Monitoring | AP15: Pending | AQ15: Planned | AS15: Schedule engagement on mineral supply and downstreaming alignment for battery ecosystem. | AT15: Need Follow Up
A16: 11 | B16: Kemenhan | C16: Strategic / defense use case | D16: 5 | E16: 4 | F16: 4 | G16: 4 | H16: =(D16*$B$56)+(E16*$B$57)+(F16*$B$58)+(G16*$B$59) -> 4.3 | I16: =IF(H16>=4.25,"P1",IF(H16>=3,"P2","P3")) -> P1 | J16: Hilir | K16: Pertahanan & Strategic Use Case | L16: UU No. 16/2012 (Industri Pertahanan); kebijakan pengadaan TNI, standar militer terkait | M16: Kebutuhan TNI, spesifikasi militer, kelaikan pertahanan, procurement & deployment, dukungan industri strategis | N16: Pengguna & Layanan | O16: 4. Supply Chain & Logistics; 6. User, Service & After-Sales | P16: Policy, Regulation & Standards | Q16: Strategic / defense use case | R16: WS3 – Market & Sales | S16: WS2 Ecosystem, Legal; WS3 Innovation | T16: CMO | U16: Monitoring | V16: Accompany | W16: - | X16: Defense use case & demand alignment | Z16: Kebutuhan TNI & use case | AA16: Kebutuhan TNI & use case | AB16: Kebutuhan TNI & use case | AC16: Requirement & spesifikasi | AD16: Requirement freeze | AE16: Validasi use case | AF16: Validasi use case | AG16: Validasi use case | AH16: Pengadaan & implementasi | AI16: Pengadaan & implementasi | AJ16: Pengadaan & implementasi | AK16: Pengadaan & implementasi | AL16: Monitoring | AM16: Monitoring | AN16: Monitoring | AO16: Monitoring | AP16: In Progress | AQ16: Completed | AR16: 46280 | AS16: Follow up defense use case, demand requirements and strategic alignment discussed with Kemhan. | AT16: Need Follow Up
A17: 12 | B17: TNI / Defense User | C17: Requirement & demand | D17: 5 | E17: 4 | F17: 4 | G17: 4 | H17: =(D17*$B$56)+(E17*$B$57)+(F17*$B$58)+(G17*$B$59) -> 4.3 | I17: =IF(H17>=4.25,"P1",IF(H17>=3,"P2","P3")) -> P1 | J17: Hilir | K17: Pertahanan & Strategic Use Case | L17: Kebijakan pengadaan TNI dan kebutuhan user | M17: User requirement, demand, spesifikasi, procurement/use case | N17: Pengguna & Layanan | O17: 4. Supply Chain & Logistics; 6. User, Service & After-Sales | Q17: Requirement & demand | R17: WS3 – Market & Sales | S17: WS2 Ecosystem; WS3 Innovation | T17: CMO | U17: Monitoring | V17: Accompany | W17: - | X17: User requirement / demand commitment | Z17: Diskusi kebutuhan awal | AA17: Diskusi kebutuhan awal | AB17: Diskusi kebutuhan awal | AC17: Procurement & spesifikasi | AD17: Alignment | AE17: Validasi produk | AF17: Validasi produk | AG17: Validasi produk | AH17: Uji operasional & feedback | AI17: Uji operasional & feedback | AJ17: Uji operasional & feedback | AK17: Uji operasional & feedback | AL17: Monitoring | AM17: Monitoring | AN17: Monitoring | AO17: Monitoring | AP17: Pending | AQ17: Planned | AS17: Engage defense users to validate requirements and potential demand commitment. | AT17: Need Follow Up
A18: 13 | B18: Dirjen Pothan | C18: Pertahanan & Strategic use case | D18: 5 | E18: 4 | F18: 4 | G18: 4 | H18: =(D18*$B$56)+(E18*$B$57)+(F18*$B$58)+(G18*$B$59) -> 4.3 | I18: =IF(H18>=4.25,"P1",IF(H18>=3,"P2","P3")) -> P1 | J18: Midstream | K18: Pertahanan & Strategic use case | M18: Alignment kebutuhan pertahanan, user requirement, spesifikasi, kelaikan, procurement dan peluang deployment kendaraan listrik untuk strategic use case | N18: Pengguna & Layanan | O18: 4. Supply Chain & Logistics; 6. User, Service & After-Sales | P18: Policy, Regulation & Standards | Q18: Strategic defense engagement, requirement & demand alignment | R18: WS3 – Market & Sales | S18: WS3 Innovation; WS3 Market & Sales; WS2 Ecosystem | T18: CMO | U18: Monitoring | V18: Co-Lead | W18: Partner Input | X18: Defense use case alignment, requirement definition & strategic procurement pathway | Z18: Audiensi / engagement awal | AA18: Audiensi / engagement awal | AB18: Kebutuhan & strategic use case | AC18: Kebutuhan & strategic use case | AD18: Requirement alignment | AE18: Validasi use case | AF18: Validasi use case | AG18: Validasi use case | AH18: Procurement / deployment pathway | AI18: Procurement / deployment pathway | AJ18: Procurement / deployment pathway | AK18: Procurement / deployment pathway | AL18: Monitoring | AM18: Monitoring | AN18: Monitoring | AO18: Monitoring | AP18: In Progress | AQ18: Completed | AR18: 46266 | AS18: Follow up defense use case, requirements and strategic procurement pathway after Dirjen Pothan engagement. | AT18: Need Follow Up
A19: 14 | B19: Danantara | C19: Financing ecosystem | D19: 5 | E19: 5 | F19: 5 | G19: 4 | H19: =(D19*$B$56)+(E19*$B$57)+(F19*$B$58)+(G19*$B$59) -> 4.75 | I19: =IF(H19>=4.25,"P1",IF(H19>=3,"P2","P3")) -> P1 | J19: Enablers (Financing & Support) | K19: Fiskal, Perdagangan & Pembiayaan, Program/investment/strategic partnership alignment | M19: Mandat pengelolaan dan optimalisasi investasi pemerintah/aset BUMN, tata kelola Danantara, serta pengelolaan aset; relevan untuk alignment investasi strategis dan dukungan ekosistem pembiayaan MOLINAS. | N19: Distribusi & Pasar; Pengguna & Layanan ; Manufaktur & Supply Chain; | O19: 3. Manufacturing & Assembly; 4. Supply Chain & Logistics; 5. Sales, Distribution & Market; 6. User, Service & After-Sales; 8. Financing & Investment | P19: Governance & Institutional Support | Q19: Financing ecosystem | R19: WS1 – Business Development | S19: WS2 – Ecosystem; WS4 – Finance; WS2 – Legal | T19: CTO/CMO | U19: Monitoring | V19: Co-Lead | W19: Optional | X19: Financing pathway & strategic investment alignment | AB19: Diskusi insentif & skema fiskal | AC19: Diskusi insentif & skema fiskal | AD19: Penyelarasan skema | AE19: Finalisasi skema | AF19: Finalisasi skema | AG19: Finalisasi skema | AH19: Implementasi insentif | AI19: Implementasi insentif | AJ19: Implementasi insentif | AK19: Implementasi insentif | AL19: Evaluasi | AM19: Evaluasi | AN19: Evaluasi | AO19: Evaluasi | AP19: In Progress | AQ19: Ongoing | AR19: 46289 | AS19: Continue coordination with Danantara/DDMF on timeline, budget needs, Pra-FS/FS scope and financing/program alignment. | AT19: Active
A20: 15 | B20: Himbara (Bank Mandiri, BRI BNI, BTN, BSI) | C20: Financing ecosystem | D20: 4 | E20: 4 | F20: 4 | G20: 3 | H20: =(D20*$B$56)+(E20*$B$57)+(F20*$B$58)+(G20*$B$59) -> 3.75 | I20: =IF(H20>=4.25,"P1",IF(H20>=3,"P2","P3")) -> P2 | J20: Enablers (Financing & Support) | K20: Fiskal, Perdagangan & Pembiayaan | L20: POJK pembiayaan & leasing; Ketentuan pembiayaan konsumen/fleet, green financing | M20: Pembiayaan konsumen & fleet, skema leasing, green financing, market access | N20: Distribusi & Pasar; Pengguna & Layanan | O20: 5. Sales, Distribution & Market; 6. User, Service & After-Sales; 8. Financing & Investment | Q20: Financing ecosystem | R20: WS4 – Finance | S20: WS2 Legal; WS3 Market & Sales | T20: CFO | U20: Monitoring | V20: Co-Lead | W20: Optional | X20: Financing scheme & market readiness | Z20: Diskusi awal | AA20: Diskusi awal | AB20: Skema pembiayaan | AC20: Skema pembiayaan | AD20: Alignment pembiayaan | AE20: Finalisasi skema | AF20: Finalisasi skema | AG20: Finalisasi skema | AH20: Implementasi & market access | AI20: Implementasi & market access | AJ20: Implementasi & market access | AK20: Implementasi & market access | AL20: Monitoring | AM20: Monitoring | AN20: Monitoring | AO20: Monitoring | AP20: In Progress | AQ20: Planned | AS20: Finalize and conduct financing discussion with Himbara on B2B financing scheme and market readiness. | AT20: Need Follow Up
A21: 16 | B21: Kemenaker | C21: Ketenagakerjaan dan Pengembangan SDM | D21: 4 | E21: 4 | F21: 4 | G21: 4 | H21: =(D21*$B$56)+(E21*$B$57)+(F21*$B$58)+(G21*$B$59) -> 4 | I21: =IF(H21>=4.25,"P1",IF(H21>=3,"P2","P3")) -> P2 | J21: Enablers (Logistics & SDM) | K21: Manufaktur & Perakitan, Ecosystem/capability/SDM | M21: Kebutuhan & penyerapan tenaga kerja, pengembangan kompetensi, pelatihan/upskilling-reskilling, sertifikasi tenaga kerja, serta kesiapan SDM untuk mendukung industrialisasi motor listrik nasional. | N21: Semua Tahap (Ekosistem) | O21: 3. Manufacturing & Assembly | P21: Policy, Regulation & Standards; Human Capital & Capability | Q21: Kebutuhan tenaga kerja, kompetensi, pelatihan, sertifikasi & penyerapan tenaga kerja | R21: WS2 – Ecosystem | S21: WS3 – Innovation & Operation; WS2 – Ecosystem | T21: CTO/CMO | U21: Monitoring | V21: Accompany | W21: - | X21: Workforce readiness & employment creation | Z21: Audiensi & strategic alignment | AA21: Audiensi & strategic alignment | AB21: Audiensi & strategic alignment | AC21: Audiensi & strategic alignment | AD21: Aligntment | AE21: Framework dukungan | AF21: Framework dukungan | AG21: Framework dukungan | AH21: Implementasi Insentif | AI21: Implementasi insentif | AJ21: Implementasi insentif | AK21: Implementasi insentif | AL21: Monitoring | AM21: Monitoring | AN21: Monitoring | AO21: Monitoring | AP21: Pending | AQ21: Planned | AS21: Schedule engagement on workforce requirements, competencies, training, certification and employment absorption. | AT21: Need Follow Up
A22: 17 | B22: PLN | C22: Charging & ketenagalistrikan | D22: 4 | E22: 4 | F22: 4 | G22: 3 | H22: =(D22*$B$56)+(E22*$B$57)+(F22*$B$58)+(G22*$B$59) -> 3.75 | I22: =IF(H22>=4.25,"P1",IF(H22>=3,"P2","P3")) -> P2 | J22: Enablers (Charging / Swapping) | K22: Infrastruktur Pengisian & Ketenagalistrikan | L22: Permen ESDM No. 1/2023 (SPKLU); Ketentuan ketenagalistrikan, tarif, K3 | M22: SPKLU/SPBKLU, tarif listrik, integrasi jaringan, standar teknis & keselamatan | N22: Distribusi & Pasar; Pengguna & Layanan | O22: 5. Sales, Distribution & Market; 6. User, Service & After-Sales; 7. Infrastructure & Charging | P22: Policy, Regulation & Standards | Q22: Charging & ketenagalistrikan | R22: WS3 – Innovation | S22: WS3 Supply Chain; WS2 Legal/Ecosystem | T22: CTO / COO | U22: Monitoring | V22: Accompany | W22: Technical input | X22: Charging infrastructure pathway | Z22: Mineral & hilirisasi (baterai) | AA22: Mineral & hilirisasi (baterai) | AB22: Mineral & hilirisasi (baterai) | AC22: Supply chain alignment | AD22: Kepastian pasokan & rantai pasok | AE22: Kepastian pasokan & rantai pasok | AF22: Kepastian pasokan & rantai pasok | AG22: Kepastian pasokan & rantai pasok | AH22: Implementasi rantai pasok | AI22: Implementasi rantai pasok | AJ22: Implementasi rantai pasok | AK22: Implementasi rantai pasok | AL22: Monitoring | AM22: Monitoring | AN22: Monitoring | AO22: Monitoring | AP22: Pending | AQ22: Planned | AS22: Schedule engagement with PLN on charging station infrastructure and potential Len role. | AT22: Need Follow Up
A23: 18 | B23: KLH / BPLH | C23: Battery waste & recycling | D23: 4 | E23: 3 | F23: 4 | G23: 3 | H23: =(D23*$B$56)+(E23*$B$57)+(F23*$B$58)+(G23*$B$59) -> 3.55 | I23: =IF(H23>=4.25,"P1",IF(H23>=3,"P2","P3")) -> P2 | J23: Hilir | K23: Lingkungan & Ekonomi Sirkular | L23: Permen LHK No. 9/2024 (Pengelolaan limbah baterai kendaraan listrik); Regulasi limbah B3 lainnya | M23: Pengumpulan, penyimpanan, daur ulang baterai, pengelolaan limbah B3, ekonomi sirkular | N23: Daur Ulang & Ekosistem Sirkular | O23: 9. Circular Economy & Recycling | Q23: Battery waste & recycling | R23: WS2 – Legal | S23: WS3 Innovation | T23: CTO | U23: Monitoring | V23: Support | W23: Recycling partner | X23: Circularity & compliance pathway | Z23: Audiensi | AA23: Audiensi | AB23: Regulasi baterai & daur ulang | AC23: Regulasi baterai & daur ulang | AD23: Requirement alignment | AE23: Finalisasi skema | AF23: Finalisasi skema | AG23: Finalisasi skema | AH23: Implementasi & pemantauan | AI23: Implementasi & pemantauan | AJ23: Implementasi & pemantauan | AK23: Implementasi & pemantauan | AL23: Monitoring | AM23: Monitoring | AN23: Monitoring | AO23: Monitoring | AP23: Pending | AQ23: Planned | AS23: Schedule engagement on battery waste, recycling and environmental/circularity requirements. | AT23: Need Follow Up
A24: 19 | B24: Kemendag | C24: Perdagangan / ekspor-impor | D24: 3 | E24: 4 | F24: 3 | G24: 3 | H24: =(D24*$B$56)+(E24*$B$57)+(F24*$B$58)+(G24*$B$59) -> 3.2 | I24: =IF(H24>=4.25,"P1",IF(H24>=3,"P2","P3")) -> P2 | J24: Enablers (Financing & Support) | K24: Fiskal, Perdagangan & Pembiayaan | L24: Ketentuan perdagangan/impor-ekspor | M24: Perdagangan, ekspor-impor, fasilitasi perdagangan | N24: Distribusi & Pasar | O24: 5. Sales, Distribution & Market; 8. Financing & Investment | Q24: Perdagangan / ekspor-impor | R24: WS2 – Legal | S24: WS1 Business Development; WS3 Supply Chain | T24: CMO | U24: Monitoring | V24: Accompany | W24: Partner input | X24: Trade / import-export pathway | Z24: Audiensi | AA24: Audiensi | AB24: Kebijakan ekspor-impor | AC24: Kebijakan ekspor-impor | AD24: Alignment | AE24: Fasilitasi perdagangan | AF24: Fasilitasi perdagangan | AG24: Fasilitasi perdagangan | AH24: Implementasi | AI24: Implementasi | AJ24: Implementasi | AK24: Implementasi | AL24: Monitoring | AM24: Monitoring | AN24: Monitoring | AO24: Monitoring | AP24: Pending | AQ24: Planned | AS24: Schedule engagement on trade/export-import policy and requirements relevant to MOLINAS. | AT24: Need Follow Up
A25: 20 | B25: OJK | C25: Financing ecosystem | D25: 4 | E25: 4 | F25: 4 | G25: 3 | H25: =(D25*$B$56)+(E25*$B$57)+(F25*$B$58)+(G25*$B$59) -> 3.75 | I25: =IF(H25>=4.25,"P1",IF(H25>=3,"P2","P3")) -> P2 | J25: Enablers (Financing & Support) | K25: Fiskal, Perdagangan & Pembiayaan | L25: POJK pembiayaan & leasing; Ketentuan pembiayaan konsumen/fleet, green financing | M25: Pembiayaan konsumen & fleet, skema leasing, green financing, market access | N25: Distribusi & Pasar; Pengguna & Layanan | O25: 5. Sales, Distribution & Market; 6. User, Service & After-Sales; 8. Financing & Investment | Q25: Financing ecosystem | R25: WS4 – Finance | S25: WS2 Legal; WS3 Market & Sales | T25: CFO | U25: Monitoring | V25: Co-Lead | W25: Optional | X25: Financing scheme & market readiness | Z25: Diskusi awal | AA25: Diskusi awal | AB25: Skema pembiayaan | AC25: Skema pembiayaan | AD25: Alignment pembiayaan | AE25: Finalisasi skema | AF25: Finalisasi skema | AG25: Finalisasi skema | AH25: Implementasi & market access | AI25: Implementasi & market access | AJ25: Implementasi & market access | AK25: Implementasi & market access | AL25: Monitoring | AM25: Monitoring | AN25: Monitoring | AO25: Monitoring | AP25: Pending | AQ25: Planned | AS25: Schedule engagement on financing ecosystem and relevant regulatory considerations. | AT25: Need Follow Up
A26: 21 | B26: BSN | C26: Standardisasi / SNI | D26: 4 | E26: 4 | F26: 4 | G26: 4 | H26: =(D26*$B$56)+(E26*$B$57)+(F26*$B$58)+(G26*$B$59) -> 4 | I26: =IF(H26>=4.25,"P1",IF(H26>=3,"P2","P3")) -> P2 | J26: Hulu | K26: Baterai & Teknologi Baterai; Chassis/Rangka & Komponen Kendaraan; Standardisasi | M26: Standardisasi, penyusunan/validasi SNI, conformity assessment | N26: Manufaktur & Supply Chain; Pengguna & Layanan | O26: 1. Engineering, Technology & R&D; 2. Raw Materials & Components; 3. Manufacturing & Assembly; 4. Supply Chain & Logistics; 6. User, Service & After-Sales | P26: Policy, Regulation & Standards; Technology, Data & Digital | Q26: Standardisasi / SNI | R26: WS2 – Ecosystem | S26: WS2 Legal; WS3 Innovation | T26: CTO | U26: Monitoring | V26: Support | W26: Technical input | X26: Standardization / SNI alignment | Z26: Audiensi | AA26: Audiensi | AB26: Standardisasi / SNI | AC26: Standardisasi / SNI | AD26: Alignment standar | AE26: Finalisasi standar | AF26: Finalisasi standar | AG26: Finalisasi standar | AH26: Conformity assessment & sertifikasi | AI26: Conformity assessment & sertifikasi | AJ26: Conformity assessment & sertifikasi | AK26: Conformity assessment & sertifikasi | AL26: Monitoring | AM26: Monitoring | AN26: Monitoring | AO26: Monitoring | AP26: Pending | AQ26: Planned | AS26: Schedule engagement on battery standardization/SNI, including the MOLINAS battery standardization workshop. | AT26: Need Follow Up
A27: 22 | B27: LSPro | C27: Sertifikasi | D27: 4 | E27: 4 | F27: 4 | G27: 4 | H27: =(D27*$B$56)+(E27*$B$57)+(F27*$B$58)+(G27*$B$59) -> 4 | I27: =IF(H27>=4.25,"P1",IF(H27>=3,"P2","P3")) -> P2 | J27: Hulu | K27: Baterai & Teknologi Baterai; Chassis/Rangka & Komponen Kendaraan. | L27: SNI baterai & keselamatan; SNI komponen kelistrikan; SNI kendaraan/rangka, rem, suspensi, dll. | M27: Conformity assessment, sertifikasi | N27: Manufaktur & Supply Chain; Pengguna & Layanan | O27: 1. Engineering, Technology & R&D; 2. Raw Materials & Components; 3. Manufacturing & Assembly; 4. Supply Chain & Logistics; 6. User, Service & After-Sales | P27: Policy, Regulation & Standards; Technology, Data & Digital | Q27: Sertifikasi | R27: WS2 – Ecosystem | S27: WS2 Legal; WS3 Innovation | T27: CTO | U27: Monitoring | V27: Support | W27: Technical input | X27: Sertifikasi | Z27: Audiensi | AA27: Audiensi | AB27: Standardisasi / SNI | AC27: Standardisasi / SNI | AD27: Alignment standar | AE27: Finalisasi standar | AF27: Finalisasi standar | AG27: Finalisasi standar | AH27: Conformity assessment & sertifikasi | AI27: Conformity assessment & sertifikasi | AJ27: Conformity assessment & sertifikasi | AK27: Conformity assessment & sertifikasi | AL27: Monitoring | AM27: Monitoring | AN27: Monitoring | AO27: Monitoring | AP27: Pending | AQ27: Planned | AS27: Schedule engagement on certification pathway and certification requirements. | AT27: Need Follow Up
A28: 23 | B28: Puslaik Kemhan | C28: Military qualification | D28: 4 | E28: 2 | F28: 4 | G28: 3 | H28: =(D28*$B$56)+(E28*$B$57)+(F28*$B$58)+(G28*$B$59) -> 3.35 | I28: =IF(H28>=4.25,"P1",IF(H28>=3,"P2","P3")) -> P2 | J28: Hilir | K28: Pertahanan & Strategic Use Case | L28: UU No. 16/2012 (Industri Pertahanan); standar/kebijakan kelaikan pertahanan | M28: Persyaratan sertifikasi dan kualifikasi militer, uji dan validasi | N28: Pengguna & Layanan | O28: 6. User, Service & After-Sales | P28: Policy, Regulation & Standards | Q28: Military qualification | R28: WS3 – Market & Sales | S28: WS3 Innovation; WS3 Market & Sales | T28: CTO | U28: Monitoring | V28: Accompany | W28: Technical input | X28: Military qualification pathway | Z28: Persyaratan sertifikasi | AA28: Persyaratan sertifikasi | AB28: Persyaratan sertifikasi | AC28: Proses sertifikasi | AD28: Certification plan | AE28: Uji & validasi | AF28: Uji & validasi | AG28: Uji & validasi | AH28: Sertifikasi & deployment | AI28: Sertifikasi & deployment | AJ28: Sertifikasi & deployment | AK28: Sertifikasi & deployment | AL28: Monitoring | AM28: Monitoring | AN28: Monitoring | AO28: Monitoring | AP28: Pending | AQ28: Planned | AS28: Schedule engagement on military qualification requirements for MOLINAS use cases. | AT28: Need Follow Up
A29: 24 | B29: Grab* | C29: Offtake / fleet | D29: 3 | E29: 4 | F29: 3 | G29: 3 | H29: =(D29*$B$56)+(E29*$B$57)+(F29*$B$58)+(G29*$B$59) -> 3.2 | I29: =IF(H29>=4.25,"P1",IF(H29>=3,"P2","P3")) -> P2 | J29: Hilir | K29: Pengguna / Offtaker | L29: Ketentuan operasional/fleet yang relevan | M29: Offtake, kebutuhan fleet, model bisnis, pilot dan implementasi fleet | N29: Pengguna & Layanan | O29: 5. Sales, Distribution & Market; 6. User, Service & After-Sales | P29: Policy, Regulation & Standards | Q29: Offtake / fleet | R29: WS3 – Market & Sales | S29: WS2 Ecosystem; WS3 Innovation | T29: CMO | U29: Monitoring | V29: Accompany | W29: OEM support | X29: Offtake / fleet demand | Z29: Diskusi kebutuhan awal | AA29: Diskusi kebutuhan awal | AB29: Diskusi kebutuhan awal | AC29: Kebutuhan fleet & model bisnis | AD29: Alignment komersial | AE29: Pilot / uji coba | AF29: Pilot / uji coba | AG29: Pilot / uji coba | AH29: Implementasi fleet | AI29: Implementasi fleet | AJ29: Implementasi fleet | AK29: Implementasi fleet | AL29: Monitoring | AM29: Monitoring | AN29: Monitoring | AO29: Monitoring | AP29: Pending | AQ29: Planned | AS29: Prioritize engagement with Grab to validate fleet/offtake requirements and potential demand. | AT29: Need Follow Up
A30: 25 | B30: Gojek* | C30: Offtake / fleet | D30: 3 | E30: 4 | F30: 3 | G30: 3 | H30: =(D30*$B$56)+(E30*$B$57)+(F30*$B$58)+(G30*$B$59) -> 3.2 | I30: =IF(H30>=4.25,"P1",IF(H30>=3,"P2","P3")) -> P2 | J30: Hilir | K30: Pengguna / Offtaker | L30: Ketentuan operasional/fleet yang relevan | M30: Offtake, kebutuhan fleet, model bisnis, pilot dan implementasi fleet | N30: Pengguna & Layanan | O30: 5. Sales, Distribution & Market; 6. User, Service & After-Sales | P30: Policy, Regulation & Standards | Q30: Offtake / fleet | R30: WS3 – Market & Sales | S30: WS2 Ecosystem; WS3 Innovation | T30: CMO | U30: Monitoring | V30: Accompany | W30: OEM support | X30: Offtake / fleet demand | Z30: Diskusi kebutuhan awal | AA30: Diskusi kebutuhan awal | AB30: Diskusi kebutuhan awal | AC30: Kebutuhan fleet & model bisnis | AD30: Alignment komersial | AE30: Pilot / uji coba | AF30: Pilot / uji coba | AG30: Pilot / uji coba | AH30: Implementasi fleet | AI30: Implementasi fleet | AJ30: Implementasi fleet | AK30: Implementasi fleet | AL30: Monitoring | AM30: Monitoring | AN30: Monitoring | AO30: Monitoring | AP30: Pending | AQ30: Planned | AS30: Prioritize engagement with Gojek to validate fleet/offtake requirements and potential demand. | AT30: Need Follow Up
A31: 26 | B31: Pos Indonesia | C31: Commercial fleet | D31: 3 | E31: 4 | F31: 3 | G31: 3 | H31: =(D31*$B$56)+(E31*$B$57)+(F31*$B$58)+(G31*$B$59) -> 3.2 | I31: =IF(H31>=4.25,"P1",IF(H31>=3,"P2","P3")) -> P2 | J31: Enablers (Logistics & SDM) | K31: Pengguna / Offtaker | L31: Ketentuan operasional/fleet yang relevan | M31: Kebutuhan armada, pilot fleet, deployment komersial | N31: Pengguna & Layanan | O31: 5. Sales, Distribution & Market; 6. User, Service & After-Sales | P31: Human Capital & Capability | Q31: Commercial fleet | R31: WS3 – Market & Sales | S31: WS2 Ecosystem; WS4 Finance, WS3 Supply Chain | T31: CMO | U31: Monitoring | V31: Accompany | W31: OEM support | X31: Fleet deployment | Z31: Diskusi kebutuhan awal | AA31: Diskusi kebutuhan awal | AB31: Diskusi kebutuhan awal | AC31: Kebutuhan armada | AD31: Alignment deployment | AE31: Pilot fleet | AF31: Pilot fleet | AG31: Pilot fleet | AH31: Deployment awal | AI31: Deployment awal | AJ31: Deployment awal | AK31: Deployment awal | AL31: Monitoring | AM31: Monitoring | AN31: Monitoring | AO31: Monitoring | AP31: Pending | AQ31: Planned | AS31: Engage Pos Indonesia to validate commercial fleet requirements and potential deployment. | AT31: Need Follow Up
A32: 27 | B32: JNE | C32: Commercial fleet | D32: 3 | E32: 4 | F32: 3 | G32: 3 | H32: =(D32*$B$56)+(E32*$B$57)+(F32*$B$58)+(G32*$B$59) -> 3.2 | I32: =IF(H32>=4.25,"P1",IF(H32>=3,"P2","P3")) -> P2 | J32: Enablers (Logistics & SDM) | K32: Pengguna / Offtaker | L32: Ketentuan operasional/fleet yang relevan | M32: Kebutuhan armada, pilot fleet, deployment komersial | N32: Pengguna & Layanan | O32: 5. Sales, Distribution & Market; 6. User, Service & After-Sales | P32: Human Capital & Capability | Q32: Commercial fleet | R32: WS3 – Market & Sales | S32: WS2 Ecosystem; WS4 Finance, WS3 Supply Chain | T32: CMO | U32: Monitoring | V32: Accompany | W32: OEM support | X32: Fleet deployment | Z32: Diskusi kebutuhan awal | AA32: Diskusi kebutuhan awal | AB32: Diskusi kebutuhan awal | AC32: Kebutuhan armada | AD32: Alignment deployment | AE32: Pilot fleet | AF32: Pilot fleet | AG32: Pilot fleet | AH32: Deployment awal | AI32: Deployment awal | AJ32: Deployment awal | AK32: Deployment awal | AL32: Monitoring | AM32: Monitoring | AN32: Monitoring | AO32: Monitoring | AP32: Pending | AQ32: Planned | AS32: Engage JNE to validate commercial fleet requirements and potential deployment. | AT32: Need Follow Up
A33: 28 | B33: AESMOLI | C33: Industry association / ecosystem coordination | D33: 3 | E33: 4 | F33: 3 | G33: 3 | H33: =(D33*$B$56)+(E33*$B$57)+(F33*$B$58)+(G33*$B$59) -> 3.2 | I33: =IF(H33>=4.25,"P1",IF(H33>=3,"P2","P3")) -> P2 | J33: Hilir | K33: Industry association / ecosystem coordination | M33: Koordinasi pelaku industri, penyampaian masukan kebijakan, alignment kebutuhan industri, serta penguatan kolaborasi ekosistem | N33: Semua Tahap (Ekosistem) | O33: Perlu validasi | P33: Policy, Regulation & Standards | Q33: Industry alignment, policy input & ecosystem coordination | R33: WS2 – Ecosystem | S33: WS1 Business Development; WS3 Innovation & Market | T33: CMO | U33: Monitoring | V33: Accompany | W33: Partner / OEM | X33: Industry alignment, policy input & ecosystem collaboration | Z33: Audiensi / engagement awal | AA33: Audiensi / engagement awal | AB33: Industry input & policy discussion | AC33: Industry input & policy discussion | AD33: Alignment program | AE33: Alignment program | AF33: Alignment program | AG33: Alignment program | AH33: Koordinasi implementasi | AI33: Koordinasi implementasi | AJ33: Koordinasi implementasi | AK33: Koordinasi implementasi | AL33: Monitoring | AM33: Monitoring | AN33: Monitoring | AO33: Monitoring | AP33: Pending | AQ33: Planned | AS33: Continue industry alignment and policy discussion; validate AESMOLI role and concrete engagement scope. | AT33: Need Follow Up
A34: 29 | B34: Mitra terkait* | C34: Model bisnis / struktur kemitraan | D34: 3 | E34: 4 | F34: 3 | G34: 3 | H34: =(D34*$B$56)+(E34*$B$57)+(F34*$B$58)+(G34*$B$59) -> 3.2 | I34: =IF(H34>=4.25,"P1",IF(H34>=3,"P2","P3")) -> P2 | J34: Hulu | K34: Business Model / Partnership | L34: Regulasi korporasi, investasi, pembiayaan dan partnership yang relevan | M34: Struktur kemitraan, commercial model validation | N34: Semua Tahap (Ekosistem) | O34: Perlu validasi | Q34: Model bisnis / struktur kemitraan | R34: WS1 – Business Development | S34: WS3 Market & Sales, Innovation; WS2 Legal/Ecosystem | T34: CMO | U34: Monitoring | V34: Co-Lead | W34: Partner input | X34: Commercial model validation | Y34: Partner mapping & engagement setup | Z34: Audiensi / engagement awal | AA34: Audiensi / engagement awal | AB34: Diskusi kebutuhan awal | AC34: Alignment kebutuhan fleet / armada | AD34: Alignment komersial / deployment | AE34: Koordinasi uji coba | AF34: Koordinasi uji coba | AG34: Koordinasi uji coba | AH34: Koordinasi implementasi fleet / deployment | AI34: Koordinasi implementasi fleet / deployment | AJ34: Koordinasi implementasi fleet / deployment | AK34: Koordinasi implementasi fleet / deployment | AL34: Monitoring | AM34: Monitoring | AN34: Monitoring | AO34: Monitoring | AP34: Pending | AQ34: Planned | AS34: Identify the specific partner entity and schedule engagement to validate business model and partnership structure. | AT34: Need Follow Up
A35: 30 | B35: ATMI | C35: Manufaktur & Supply Chain | D35: 4 | E35: 4 | F35: 4 | G35: 4 | H35: =(D35*$B$56)+(E35*$B$57)+(F35*$B$58)+(G35*$B$59) -> 4 | I35: =IF(H35>=4.25,"P1",IF(H35>=3,"P2","P3")) -> P2 | J35: Midstream | K35: Mold Making, Plastic Injection, Product Development & Vocational Education | L35: Permenkominfo No. 3/2024 (Sertifikasi alat/perangkat telekomunikasi); SNI, standar komunikasi kendaraan | M35: Tool making, plastic injection, product development, scientific molding, mold assembly, training/certification, capacity building untuk mendukung MOLINAS | N35: Manufaktur & Supply Chain; Pengguna & Layanan | O35: 3. Manufacturing & Assembly; 4. Supply Chain & Logistics; 6. User, Service & After-Sales | P35: Human Capital & Capability | Q35: Design enhancement & mass-production preparation | R35: WS2 – Ecosystem | S35: WS3 – Innovation, Supply Chain; WS2 – Legal | T35: CTO / CMO | U35: Monitoring | V35: Co-Lead | W35: Technical / vocational partner | X35: Readiness mold & plastic injection, capacity building, training, dan industrial ecosystem support | Z35: Audiensi | AA35: Audiensi | AB35: Scope alignment | AC35: Capability validation | AD35: Capability validation | AE35: Program design | AF35: Program design | AG35: Implementation preparation | AH35: Implementation | AI35: Implementation | AJ35: Implementation | AK35: Readiness review | AL35: Readiness review | AM35: Evaluation | AN35: Evaluation | AO35: Evaluation | AP35: Pending | AQ35: Planned | AS35: Schedule engagement to align scope for design enhancement, mold/plastic injection readiness, training and mass-production preparation. | AT35: Need Follow Up
A36: 31 | B36: Adyawinsa Group | C36: Manufaktur & Supply Chain | D36: 5 | E36: 4 | F36: 3 | G36: 4 | H36: =(D36*$B$56)+(E36*$B$57)+(F36*$B$58)+(G36*$B$59) -> 4.05 | I36: =IF(H36>=4.25,"P1",IF(H36>=3,"P2","P3")) -> P2 | J36: Midstream | K36: Design & Engineering; Frame & Chassis; Plastic Injection; Electrical & Power; Mass Production | L36: Permenkominfo No. 3/2024 (Sertifikasi alat/perangkat telekomunikasi); SNI, standar komunikasi kendaraan | M36: Design enhancement, FMEA, engineering, detailed BOM/process, production line & plant readiness, component sourcing, frame/chassis, plastic injection, electrical & power, quality assurance, dan mass-production preparation | N36: Manufaktur & Supply Chain; Distribusi & Pasar | O36: 1. Engineering, Technology & R&D; 3. Manufacturing & Assembly; 4. Supply Chain & Logistics; 5. Sales, Distribution & Market | R36: WS3 – Innovation | S36: WS2 – Ecosystem; WS1 – Business Development | T36: CTO / COO | U36: Monitoring | V36: Co-Lead | W36: Manufacturing / engineering partner | X36: Design & engineering readiness, supply-chain support, plant readiness, dan mass-production pathway | Z36: Audiensi | AA36: Audiensi | AB36: Design enhancement | AC36: Design enhancement | AD36: Engineering / FMEA | AE36: Engineering / FMEA | AF36: Engineering GO | AG36: Tooling & production preparation | AH36: Tooling & production preparation | AI36: Trial / product verification | AJ36: Trial / quality approval | AK36: Mass-production preparation | AL36: Mass-production preparation | AM36: Readiness review | AN36: Readiness review | AO36: Evaluation | AP36: Pending | AQ36: Planned | AR36: 46290 | AS36: Conduct scheduled visit with Matius – Adyawinsa and capture follow-up actions. | AT36: Active
A37: 32 | B37: Komdigi | C37: Connectivity / IoT | D37: 2 | E37: 2 | F37: 2 | G37: 2 | H37: =(D37*$B$56)+(E37*$B$57)+(F37*$B$58)+(G37*$B$59) -> 2 | I37: =IF(H37>=4.25,"P1",IF(H37>=3,"P2","P3")) -> P3 | J37: Enablers (Technology, Data & Digital) | K37: Konektivitas & Digital | L37: Permenkominfo No. 3/2024 (Sertifikasi alat/perangkat telekomunikasi); SNI, standar komunikasi kendaraan | M37: IoT/TCU, GPS, 4G/5G, perangkat komunikasi, keamanan data, standardisasi | N37: Pengguna & Layanan | O37: 6. User, Service & After-Sales | P37: Policy, Regulation & Standards; Technology, Data & Digital | Q37: Pengembangan ekosistem mold making, plastic injection & vocational capacity | R37: WS3 – Innovation | S37: WS2 Legal | T37: CTO | U37: Monitoring | V37: Support | W37: Technology partner | X37: Digital/connectivity compliance | Z37: Audiensi | AA37: Audiensi | AB37: Diskusi IoT/TCU & standar | AC37: Diskusi IoT/TCU & standar | AD37: Alignment teknis | AE37: Pilot & integrasi | AF37: Pilot & integrasi | AG37: Pilot & integrasi | AH37: Implementasi (jika relevan) | AI37: Implementasi (jika relevan) | AJ37: Implementasi (jika relevan) | AK37: Implementasi (jika relevan) | AL37: Monitoring | AM37: Monitoring | AN37: Monitoring | AO37: Monitoring | AP37: Pending | AQ37: Planned | AS37: Schedule engagement on digital/connectivity ecosystem, including mold making, plastic injection and vocational capacity. | AT37: Need Follow Up
A42: MOLINAS PROGRAM MILESTONES
A43: Agt W1 | B43: Program Mobilization & Stakeholder Mapping
A44: Sep W4 | B44: Regulatory Clarity & Key Decision Closure
A45: Okt W4 | B45: Finalisasi Spesifikasi & FS / Production Preparation
A46: Nov W4 | B46: Production Ramp Up & Certification
A47: Des W4 | B47: Initial Delivery & Customer Deployment
A49: LEGEND | B49: Roadmap activity | C49: Schedule inferred from PIC + regulatory dependency | I49: P1 – Gatekeeper | K49: P2 – Scale Enabler | L49: P3 – Conditional | M49: P3 - Support / Kondisional
A50: LEGEND (Tahap Ekosistem) | B50: Bahan Baku & Komponen Dasar | C50: Manufaktur & Supply Chain | D50: Infrastruktur & Pendukung | G50: Distribusi & Pasar | I50: Pengguna & Layanan | K50: Daur Ulang & Ekosistem Sirkular
A52: LEGEND (Value Chain Layer) | B52: Engineering, Technology & R&D | C52: Raw Materials & Components | D52: Manufacturing & Assembly | G52: Supply Chain & Logistics | I52: Sales, Distribution & Market | K52: User, Service & After-Sales | M52: Infrastructure & Charging | N52: Financing & Investment | O52: Circular Economy & Recycling
A53: LEGEND (Cross-Cutting Enabler) | B53: Policy, Regulation & Standards | C53: Human Capital & Capability | D53: Technology, Data & Digital | G53: Governance & Institutional Support
A55: KRITERIA PRIORITAS
A56: Criticality | B56: 0.3
A57: Breadth of Impact | B57: 0.2
A58: Depedency | B58: 0.25
A59: Urgency | B59: 0.25
A61: Weighted Score | B61: Priority
A62: ≥ 4,25 | B62: P1
A63: 3,00 - < 4,25 | B63: P2
A64: < 3,00 | B64: P3

Sheet KRITERIA PRIORITAS (SCORING)
A1: KRITERIA PENILAIAN & SCORING PRIORITAS WS2
A2: Penilaian menggunakan skala 1–5; setiap score dikalikan bobot kriteria untuk memperoleh Priority Score.
A4: Priority Score = (Criticality × 30%) + (Program Dependency × 25%) + (Urgency × 25%) + (Breadth of Impact × 20%)
A6: Kriteria | B6: Bobot | C6: Definisi Kriteria | D6: 1 – Sangat Rendah | E6: 2 – Rendah | F6: 3 – Menengah | G6: 4 – Tinggi | H6: 5 – Sangat Tinggi
A7: Criticality | B7: 0.3 | C7: Mengukur tingkat keparahan konsekuensi apabila stakeholder/regulasi tidak tertangani terhadap keberhasilan program. | D7: Konsekuensi sangat terbatas; tidak memengaruhi aktivitas utama, milestone, atau target program dan dapat ditangani melalui proses rutin. | E7: Gangguan terbatas pada aktivitas tertentu; tidak berdampak signifikan terhadap milestone utama dan masih mudah dimitigasi. | F7: Dampak material pada satu atau beberapa aktivitas penting; membutuhkan koordinasi/mitigasi aktif, namun masih dapat dipulihkan. | G7: Berpotensi mengganggu milestone kritis atau menimbulkan keterlambatan berantai; membutuhkan intervensi lintas pihak yang signifikan. | H7: Berpotensi menghentikan aktivitas fundamental, menggagalkan mandatory requirement/approval, atau menyebabkan target utama tidak tercapai; ruang recovery sangat terbatas.
A8: Dependency | B8: 0.25 | C8: Mengukur tingkat ketergantungan program terhadap stakeholder/regulasi sebagai prasyarat untuk menjalankan atau melanjutkan tahapan berikutnya. | D8: Bukan prasyarat; aktivitas tetap dapat berjalan tanpa stakeholder/regulasi dan tersedia alternatif yang setara. | E8: Berperan sebagai supporting enabler; ketidakterlibatan masih dapat diatasi dengan alternatif dan penyesuaian kecil. | F8: Menjadi input/enabler penting; alternatif masih tersedia tetapi membutuhkan tambahan waktu, effort, atau koordinasi. | G8: Menjadi key prerequisite bagi milestone/tahapan berikutnya; alternatif terbatas dan keterlambatan berpotensi menahan progress. | H8: Menjadi mandatory prerequisite/single point of dependency; tahapan berikutnya tidak dapat berjalan secara feasible tanpa pemenuhannya.
A9: Urgency | B9: 0.25 | C9: Mengukur kebutuhan waktu untuk memulai engagement/tindak lanjut berdasarkan lead time, dependency, milestone, dan buffer menuju target akhir Desember. | D9: Belum membutuhkan engagement dalam waktu dekat; buffer sangat memadai dan penundaan tidak berdampak material. | E9: Engagement perlu dipersiapkan, namun masih tersedia fleksibilitas waktu dan buffer tanpa memengaruhi milestone utama. | F9: Engagement perlu dimulai dalam waktu dekat karena membutuhkan lead time tertentu; penundaan mulai mengurangi buffer penyelesaian. | G9: Engagement perlu segera diinisiasi karena lead time, dependency berurutan, atau milestone yang semakin berdekatan membuat ruang waktu terbatas. | H9: Memerlukan immediate prioritization; lead time kritis atau buffer sangat terbatas sehingga keterlambatan memulai berpotensi langsung mengancam target akhir Desember.
A10: Breadth of Impact | B10: 0.2 | C10: Mengukur luasnya tahapan, workstream, dan stakeholder yang terdampak apabila stakeholder/regulasi tidak tertangani. | D10: Dampak terbatas pada satu aktivitas atau satu stakeholder dan tidak memengaruhi proses lain secara berarti. | E10: Dampak mencakup beberapa aktivitas dalam satu tahapan/workstream, tetapi belum menyebar secara signifikan. | F10: Dampak meluas ke beberapa aktivitas atau lebih dari satu workstream dan membutuhkan koordinasi lintas pihak. | G10: Dampak mencakup beberapa tahapan rantai nilai dan berbagai stakeholder, dengan potensi gangguan/keterlambatan berantai. | H10: Dampak lintas tahapan, lintas fungsi, dan/atau lintas kelompok stakeholder; berpotensi menimbulkan cascading impact pada sebagian besar ekosistem.
A12: ANCHOR PENILAIAN
A13: Criticality | B13: Seberapa fatal konsekuensinya apabila stakeholder/isu tidak tertangani?
A14: Program Dependency | B14: Seberapa essential stakeholder/regulasi tersebut agar tahapan berikutnya dapat berjalan?
A15: Urgency | B15: Seberapa segera engagement/tindak lanjut perlu dimulai untuk menjaga timeline dan buffer?
A16: Breadth of Impact | B16: Seberapa luas tahapan, workstream, dan stakeholder yang terdampak?

Sheet DASAR STAKEHOLDER & REGULASI
A1: No | B1: Stakeholder/Lembaga | C1: Regulasi | D1: Tentang | E1: Keterangan
A2: 1 | B2: Kemenperin | C2: Permenperin No. 6 Tahun 2022 jo. No. 28 Tahun 2023 (Ps. 2, 3, 4, 11, 11A, 12, 12A) | D2: Spesifikasi, Peta Jalan Pengembangan, dan Penghitungan Nilai TKDN KBLBB | E2: Mengatur spesifikasi KBLBB termasuk roda dua/tiga, peta jalan pengembangan industri, serta penghitungan nilai TKDN, struktur komponen, dan ketentuan baterai.
C3: Permenperin No. 29 Tahun 2023 (Ps. 2–5, 8–15, 18–20) | D3: KBLBB dalam Keadaan Terurai Lengkap dan Tidak Lengkap (CKD/IKD) | E3: Mengatur ketentuan impor KBLBB dalam bentuk CKD/IKD, kewajiban proses manufaktur dalam negeri, serta ketentuan perakitan, pengujian, pengendalian mutu, dan pelaporan.
C4: Permenperin No. 35 Tahun 2025 (Ps. 4, 6, 9, 10, 39–45, 73) | D4: Ketentuan dan Tata Cara Sertifikasi TKDN dan BMP | E4: Mengatur tata cara penghitungan, verifikasi, sertifikasi, surveilans, dan pengawasan TKDN/BMP, termasuk integrasinya dengan ketentuan khusus KBLBB pada Pasal 73.
C5: Permenperin No. 37 Tahun 2025 | D5: Standar Kegiatan Usaha dan Standar Produk/Jasa dalam Perizinan Berusaha Berbasis Risiko Sektor Perindustrian | E5: Mengatur standar kegiatan usaha dan standar produk/jasa sektor perindustrian sebagai dasar pemenuhan perizinan berusaha berbasis risiko.
C6: Permenperin No. 3 Tahun 2026 | D6: Tata Cara Penerbitan Pertimbangan Teknis dalam rangka Pembebasan Bea Masuk | E6: Mengatur penerbitan dan verifikasi pertimbangan teknis serta fasilitas pembebasan Bea Masuk untuk mesin, barang, dan/atau bahan yang digunakan dalam pembangunan industri dan kegiatan R&D.
C7: Permenperin No. 5 Tahun 2026 | D7: Pusat Penyediaan Bahan Baku dan/atau Bahan Penolong | E7: Mengatur pusat penyediaan bahan baku dan/atau bahan penolong, termasuk ketentuan impor, verifikasi, serta monitoring untuk mendukung kelancaran pasokan industri.
C8: Permenperin No. 6 Tahun 2023 jo. No. 21 Tahun 2023 (Ps. 3 dan ketentuan perubahan Permenperin No. 21/2023) | D8: Pedoman Pemberian Bantuan Pemerintah untuk Pembelian KBLBB Roda Dua | E8: Mengatur pedoman pemberian bantuan pemerintah untuk pembelian KBLBB roda dua, termasuk kriteria penerima, mekanisme, dan pelaksanaan program.
C9: Permenperin No. 23 Tahun 2021 jo. No. 37 Tahun 2021 | D9: Industri Kendaraan Bermotor Roda Empat atau Lebih | E9: Mengatur ketentuan industri dan manufaktur kendaraan bermotor roda empat atau lebih sebagai benchmark pengembangan industri, rantai pasok, dan peningkatan daya saing.
C10: UU No. 3 Tahun 2014 tentang Perindustrian | D10: Pembangunan dan pengembangan industri nasional | E10: Menjadi dasar pengembangan industri dan manufaktur MOLINAS, termasuk peningkatan TKDN dan industri komponen
C11: PP No. 28 Tahun 2023 tentang Peraturan Pelaksanaan UU Perindustrian | D11: Pelaksanaan pembangunan industri | E11: Mendukung industrialisasi MOLINAS, penguatan rantai pasok, teknologi, dan kapasitas produksi dalam negeri.
A12: 2 | B12: Kemenhub | C12: Permenhub No. 87/2020 (Uji Tipe KBLBB) | D12: Mengatur pengujian tipe fisik Kendaraan Bermotor Listrik Berbasis Baterai (KBLBB). | E12: Menjadi dasar type approval/uji tipe kendaraan listrik yang harus dipenuhi produk MOLINAS sebelum dapat dioperasikan sesuai ketentuan transportasi jalan.
C13: UU No. 22 Tahun 2009 tentang Lalu Lintas dan Angkutan Jalan | D13: Mengatur penyelenggaraan lalu lintas dan angkutan jalan, termasuk persyaratan kendaraan bermotor, keselamatan, serta penggunaan kendaraan di jalan. | E13: Landasan legal kendaraan MOLINAS. Menjadi dasar agar kendaraan listrik yang dikembangkan dapat memenuhi persyaratan keselamatan, laik jalan, dan dapat digunakan secara legal di jalan umum.
C14: Permenhub No. 18 Tahun 2021 tentang Pengujian Tipe Kendaraan Bermotor | D14: Mengatur pengujian tipe kendaraan bermotor, yaitu proses memastikan kendaraan memenuhi persyaratan teknis dan laik jalan sebelum diproduksi/dipasarkan secara massal. | E14: Gatekeeper sebelum MOLINAS dipasarkan. Prototipe/produk MOLINAS perlu memenuhi persyaratan teknis dan pengujian tipe agar dapat diproduksi dan dioperasikan secara legal.
C15: Permenhub No. 13 Tahun 2021 tentang Registrasi dan Identifikasi Kendaraan Bermotor | D15: Mengatur proses registrasi dan identifikasi kendaraan, termasuk penerbitan dokumen dan identitas kendaraan bermotor. | E15: Legalitas dan identitas MOLINAS. Setelah memenuhi persyaratan teknis, kendaraan MOLINAS perlu diregistrasikan dan diidentifikasi agar dapat memperoleh legalitas untuk beroperasi di jalan.
C16: PP No. 55 Tahun 2012 tentang Kendaraan | D16: Mengatur persyaratan teknis dan laik jalan kendaraan, termasuk aspek konstruksi, perlengkapan, keselamatan, dan pengujian kendaraan. | E16: Standar teknis kendaraan MOLINAS. Menjadi salah satu dasar untuk memastikan desain dan spesifikasi kendaraan memenuhi ketentuan keselamatan dan kelayakan jalan.
C17: Permenhub No. 86/2020 | D17: Mengatur perubahan atas ketentuan pengujian tipe fisik kendaraan bermotor dengan motor penggerak menggunakan motor listrik. | E17: Mendukung kepastian persyaratan uji tipe kendaraan listrik dalam MOLINAS, khususnya pemenuhan aspek teknis dan keselamatan kendaraan.
A18: 3 | B18: Kemenkeu | C18: UU No. 17/2006 jo. UU No. 10/1995 tentang Kepabeanan | D18: Mengatur kepabeanan, termasuk impor-ekspor, bea masuk, pemeriksaan, pengawasan, dan prosedur kepabeanan. | E18: Menjadi dasar pengaturan arus impor-ekspor motor listrik, baterai, komponen, mesin, dan bahan baku yang diperlukan untuk membangun rantai pasok MOLINAS.
C19: PMK No. 12 tahun 2025 terkait insentif/fasilitas KBLBB (PPN, PPnBM) | D19: Mengatur fasilitas fiskal/insentif yang diberikan pemerintah sesuai objek, jenis kendaraan, dan skema kebijakan yang berlaku. | E19: Relevan untuk MOLINAS dalam mengidentifikasi dan memanfaatkan fasilitas fiskal yang dapat menurunkan biaya adopsi atau mendukung investasi kendaraan listrik sesuai persyaratan.
C20: PMK No. 62 Tahun 2025 mengenai Bea Masuk | D20: Mengatur ketentuan tarif dan/atau pembebanan bea masuk atas barang impor. | E20: Mempengaruhi biaya impor komponen dan bahan baku kendaraan listrik, sehingga berdampak pada biaya produksi dan daya saing MOLINAS.
C21: PMK 176/PMK.011/2009 jo. PMK 76/2012 jo. PMK 188/PMK.011/2015 | D21: Pembebasan Bea Masuk | E21: Pembebasan Bea Masuk atas impor mesin, barang, dan bahan untuk pembangunan serta pengembangan industri, termasuk perakitan dan komponen kendaraan.
C22: PMK 26/2022 s.t.d.d. PMK 50/2026 | D22: Tarif Bea Masuk | E22: Klasifikasi barang & pembebanan tarif
C23: PMK 130/2020 jo. PMK 69/2024 | D23: Tax Holiday | E23: Pengurangan PPh Badan industri pionir
C24: PP 78/2019 jo. PMK 81/2024 s.t.d.d. PMK 1/2026 | D24: Tax Allowance | E24: Pengurangan PPh Badan atas investasi sektor tertentu
C25: PMK 81/2024 s.t.d.d. PMK 1/2026 | D25: Super Tax Deduction R&D | E25: Pengurangan bruto hingga 300%
C26: PMK 128/2019 | D26: Super Tax Deduction SDM | E26: Pengurangan bruto hingga 200%
C27: PMK 38/2023 jo. PMK 116/2023 | D27: PPN DTP | E27: KBLBB roda 4 & bus tertentu – TA 2023
C28: PMK 8/2024 | D28: PPN DTP | E28: KBLBB roda 4 & bus tertentu – TA 2024
C29: PMK 9/2024 | D29: PPnBM DTP | E29: KBLBB roda 4 tertentu – TA 2024
C30: PMK 135/2024 | D30: PPnBM DTP | E30: KBLBB roda 4 tertentu – TA 2025
C31: PMK 12/2025 | D31: PPN/PPnBM DTP | E31: KBLBB roda 4/bus & kendaraan tertentu – TA 2025
A32: 4 | B32: Bappenas (Pihak terkait: KPPII) | C32: PP No. 42/2021 (PSN) | D32: Mengatur kemudahan dan fasilitas dalam penyelenggaraan Proyek Strategis Nasional serta percepatan pembangunan proyek yang ditetapkan sebagai PSN. | E32: Relevan apabila program/proyek MOLINAS ditetapkan atau dikaitkan dengan PSN, terutama untuk mendukung percepatan infrastruktur dan koordinasi lintas kementerian/lembaga.
C33: Permenko Perekonomian No. 20/2025 (Rencana & evaluasi PSN) | D33: Mengatur tata cara penyampaian usulan, verifikasi, evaluasi, penetapan, pemantauan, dan pelaporan perubahan daftar PSN. | E33: Relevan sebagai kerangka apabila proyek MOLINAS diusulkan/diintegrasikan dalam daftar PSN, termasuk proses evaluasi dan pemantauan proyek.
C34: Regulasi terkait penugasan BUMN | D34: Mengatur penugasan BUMN sesuai mandat pemerintah dan ruang lingkup proyek/aktivitas yang ditugaskan. | E34: Relevan apabila BUMN diberi penugasan untuk manufaktur, baterai, charging, energi, atau infrastruktur MOLINAS; regulasi spesifik mengikuti BUMN dan proyek yang bersangkutan.
A35: 5 | B35: ESDM | C35: UU No. 3 Tahun 2020 Pertambangan Mineral dan Batubara | D35: Mengatur kegiatan pertambangan mineral dan batubara, termasuk pengelolaan dan pemanfaatan mineral yang menjadi bahan baku industri. | E35: Hulu bahan baku MOLINAS. Relevan untuk menjamin ketersediaan mineral strategis yang dibutuhkan dalam rantai pasok kendaraan listrik, terutama nikel sebagai salah satu bahan baku penting industri baterai.
C36: PP No. 25 Tahun 2024 tentang Pelaksanaan Kegiatan Usaha Pertambangan Mineral dan Batubara | D36: Mengatur lebih lanjut pelaksanaan kegiatan usaha pertambangan mineral dan batubara, termasuk perizinan dan pengelolaan kegiatan pertambangan. | E36: Menjamin keberlanjutan pasokan bahan baku. Bagi MOLINAS, regulasi ini relevan pada sisi resource security, terutama jika pengembangan kendaraan nasional diarahkan untuk meningkatkan kandungan lokal dan membangun rantai pasok baterai domestik.
C37: UU No. 30 Tahun 2009 tentang Ketenagalistrikan | D37: Mengatur penyediaan, pemanfaatan, usaha, keselamatan, dan pengelolaan tenaga listrik. | E37: Fondasi ekosistem charging MOLINAS. Mobil listrik membutuhkan listrik sebagai sumber energi utama, sehingga regulasi ini menjadi dasar bagi penyediaan listrik dan infrastruktur pengisian kendaraan listrik.
C38: PP No. 14 Tahun 2012 tentang Kegiatan Usaha Penyediaan Tenaga Listrik | D38: Mengatur kegiatan usaha penyediaan tenaga listrik, termasuk penyediaan dan penjualan tenaga listrik. | E38: Mendukung operasional charging ecosystem MOLINAS. Relevan untuk memastikan ketersediaan dan mekanisme penyediaan listrik yang dibutuhkan oleh SPKLU maupun fasilitas pengisian lainnya.
C39: Permen ESDM No. 13 Tahun 2020 tentang Infrastruktur Pengisian KBLBB | D39: Mengatur infrastruktur pengisian kendaraan listrik, termasuk fasilitas charging, SPKLU, SPBKLU, aspek keselamatan, mekanisme bisnis, dan tarif listrik. | E39: Regulasi ini menjadi dasar pengembangan infrastruktur charging yang memungkinkan kendaraan MOLINAS digunakan secara luas. Namun, sudah dicabut oleh Permen ESDM No. 1 Tahun 2023, sehingga untuk laporan sebaiknya gunakan Permen ESDM No. 1/2023 sebagai regulasi yang berlaku.
C40: Permen ESDM No. 1/2023 (SPKLU) | D40: Mengatur penyediaan infrastruktur pengisian listrik untuk kendaraan bermotor listrik berbasis baterai, termasuk jenis infrastruktur, tarif, pembinaan, pengawasan, pelaporan, dan evaluasi. | E40: Menjadi dasar pengembangan infrastruktur charging MOLINAS, termasuk penyediaan dan pengoperasian SPKLU serta integrasinya dengan ekosistem kendaraan listrik.
A41: 6 | B41: Kemhan | C41: UU No. 16/2012 tentang Industri Pertahanan; kebijakan pengadaan TNI, standar militer terkait | D41: Mengatur penyelenggaraan industri pertahanan dan kemandirian industri pertahanan, termasuk pemenuhan kebutuhan alat/peralatan pertahanan. | E41: Relevan secara kondisional apabila MOLINAS mengembangkan motor listrik untuk kebutuhan pertahanan; fokus pada kemandirian industri, persyaratan teknis, dan pengadaan pertahanan.
A42: 7 | B42: TNI / Defense User | C42: Kebijakan pengadaan TNI dan kebutuhan user | D42: Mengacu pada kebutuhan operasional, spesifikasi, persyaratan teknis, dan mekanisme pengadaan pengguna pertahanan. | E42: Berperan sebagai end-user potensial apabila motor listrik MOLINAS dikembangkan untuk kebutuhan operasional TNI, termasuk penentuan spesifikasi, mission requirement, fleet, dan pengadaan.
A43: 8 | B43: Dirjen Pothan | C43: Kebijakan industri pertahanan & pengadaan | D43: Mengatur/menjalankan kebijakan terkait potensi pertahanan, industri pertahanan, dan pengadaan sesuai kewenangan Kementerian Pertahanan. | E43: Relevan apabila MOLINAS memiliki use case kendaraan listrik pertahanan, terutama untuk koordinasi kebutuhan industri, spesifikasi, kemandirian, dan pengadaan.
A44: 9 | B44: ALVA Mitra / OEM | C44: Ketentuan industri/manufaktur dan partnership yang relevan | D44: Mencakup ketentuan industri/manufaktur, TKDN, sertifikasi, uji tipe, keselamatan, mutu, produksi, dan perizinan yang berlaku bagi OEM. | E44: Sebagai OEM/mitra manufaktur potensial, berperan dalam pengembangan dan produksi kendaraan MOLINAS serta pemenuhan TKDN, type approval, standar keselamatan, quality, dan perizinan.
A45: 10 | B45: GESITS (Mitra / OEM) | C45: Ketentuan manufaktur dan partnership | D45: Mencakup ketentuan manufaktur, kerja sama/kemitraan, pengadaan komponen, kualitas, dan persyaratan produk yang relevan. | E45: Mendukung manufacturing, assembly, capacity deployment, dan integrasi produk MOLINAS sesuai spesifikasi, standar, TKDN, dan kebutuhan ekosistem.
A46: 11 | B46: Kemenaker | C46: UU No. 13 Tahun 2003 tentang Ketenagakerjaan | D46: Mengatur pembangunan ketenagakerjaan, termasuk perencanaan tenaga kerja, pelatihan kerja, penempatan tenaga kerja, perluasan kesempatan kerja, hubungan kerja, perlindungan, dan hubungan industrial. | E46: Menjadi dasar aspek ketenagakerjaan dalam MOLINAS, khususnya penyediaan, penempatan, dan peningkatan kompetensi tenaga kerja yang mendukung pengembangan industri kendaraan listrik nasional.
C47: UU No. 6 Tahun 2023 tentang Cipta Kerja | D47: Menetapkan Perppu Cipta Kerja menjadi undang-undang dan mengubah sejumlah ketentuan ketenagakerjaan serta aspek penciptaan lapangan kerja. | E47: Relevan untuk MOLINAS dalam mendukung penciptaan lapangan kerja, fleksibilitas kegiatan usaha, dan penyerapan tenaga kerja pada rantai nilai industri kendaraan listrik sesuai ketentuan yang berlaku.
C48: PP No. 33 Tahun 2013 tentang Perluasan Kesempatan Kerja | D48: Mengatur upaya pemerintah dan dunia usaha dalam menciptakan dan memperluas kesempatan kerja. | E48: Menjadi dasar pendukung MOLINAS untuk mendorong penciptaan lapangan kerja baru melalui manufaktur, komponen, baterai, charging, layanan purna jual, dan aktivitas pendukung ekosistem.
A49: 12 | B49: PLN | C49: Utility / Infrastructure Provider | D49: Berperan sebagai penyedia dan penyelenggara layanan kelistrikan serta infrastruktur pengisian kendaraan listrik sesuai kewenangan dan skema usaha yang berlaku. | E49: Menjadi enabler infrastruktur energi MOLINAS, terutama penyediaan pasokan listrik, koneksi jaringan, dan pengembangan/dukungan ekosistem charging.
A50: 13 | B50: KLH / BPLH | C50: Permen LHK No. 9/2024 | D50: Mengatur pengelolaan sampah yang mengandung B3 dan limbah B3 sesuai ruang lingkup ketentuan. | E50: Relevan untuk MOLINAS dalam pengelolaan limbah yang berasal dari baterai, komponen, proses produksi, atau aktivitas end-of-life apabila masuk kategori B3.
C51: Permen LHK No. 6 Tahun 2021 | D51: Tata Cara dan Persyaratan Pengelolaan Limbah Bahan Berbahaya dan Beracun | E51: Mengatur pengelolaan Limbah B3, termasuk kegiatan penyimpanan, pengangkutan, pemanfaatan, pengolahan, dan penimbunan. Relevan untuk limbah baterai, bahan kimia, solvent, oli, sludge, serta limbah B3 lain yang muncul sepanjang proses manufaktur dan after-sales MOLINAS.
C52: Permen LHK No. 12 Tahun 2021 | D52: Baku Mutu Emisi Daur Ulang Baterai Lithium | E52: Mengatur baku mutu emisi yang terkait dengan kegiatan daur ulang baterai lithium. Sangat relevan bagi fasilitas battery recycling/recovery MOLINAS, khususnya pengendalian emisi dari proses pemulihan material baterai.
C53: Permen LHK No. 11 Tahun 2024 | D53: Penerapan Kerangka Kualifikasi Nasional Indonesia Bidang Pengelolaan Limbah Bahan Berbahaya dan Beracun | E53: Mengatur kompetensi tenaga kerja dalam pengelolaan Limbah B3. Pelaku usaha pengelolaan Limbah B3, termasuk penghasil Limbah B3 dan kegiatan tertentu yang berisiko tinggi, diwajibkan memiliki tenaga kerja dengan kompetensi tersertifikasi sesuai ketentuan.
C54: Permen LHK No. 14 Tahun 2024 | D54: Penyelenggaraan Pengawasan dan Sanksi Administratif Bidang Lingkungan Hidup | E54: Mengatur mekanisme pengawasan, penerapan sanksi administratif, evaluasi pengawasan, pembinaan, dan ketentuan terkait penegakan kepatuhan lingkungan. Relevan sebagai compliance framework untuk fasilitas manufaktur dan pengelolaan lingkungan MOLINAS.
C55: Permen LHK No. 74 Tahun 2019 | D55: Program Kedaruratan Pengelolaan B3 dan/atau Limbah B3 | E55: Mengatur penyusunan program kedaruratan, pelatihan dan geladi, penanggulangan keadaan darurat, serta pembentukan pusat kedaruratan B3/Limbah B3. Relevan untuk mitigasi insiden seperti kebakaran baterai, tumpahan bahan kimia, atau kecelakaan dalam penyimpanan dan pengangkutan Limbah B3.
C56: Permen LHK No. 75 Tahun 2019 | D56: Peta Jalan Pengurangan Sampah oleh Produsen | E56: Mengatur pelaksanaan peta jalan pengurangan sampah oleh produsen, termasuk tugas dan kewenangan, insentif/disinsentif, serta pembiayaan. Relevan untuk membangun mekanisme pengurangan sampah dan pendekatan take-back/producer responsibility dalam ekosistem MOLINAS.
C57: Permen LHK No. 1 Tahun 2021* | D57: Program Penilaian Peringkat Kinerja Perusahaan dalam Pengelolaan Lingkungan Hidup (PROPER) | E57: Menjadi kerangka penilaian kinerja perusahaan dalam pengelolaan lingkungan. Namun, peraturan ini sudah dicabut oleh Permen LH/BPLH No. 7 Tahun 2025, sehingga untuk database yang digunakan sebagai regulatory register saat ini sebaiknya ditandai sebagai historical/reference, bukan regulasi aktif.
C58: Permen LH/BPLH No. 7 Tahun 2025 | D58: Program Penilaian Peringkat Kinerja Pengelolaan Lingkungan Hidup | E58: Regulasi yang saat ini menggantikan Permen LHK No. 1 Tahun 2021 untuk kerangka PROPER. Mengatur perencanaan, pelaksanaan, serta tindak lanjut hasil pemeringkatan kinerja pengelolaan lingkungan hidup.
C59: UU No. 1 Tahun 1970 | D59: Keselamatan kerja di tempat kerja | E59: Merupakan dasar hukum K3 di Indonesia. Mengatur kewajiban dan prinsip keselamatan kerja untuk mencegah kecelakaan serta melindungi tenaga kerja maupun pihak lain yang berada di tempat kerja. Relevan untuk fasilitas produksi, workshop, gudang, mesin produksi, instalasi listrik, bahan berbahaya, dan aktivitas operasional MOLINAS.
C60: PP No. 50 Tahun 2012 | D60: Sistem Manajemen Keselamatan dan Kesehatan Kerja (SMK3) | E60: Mengatur bagaimana perusahaan menerapkan K3 secara sistematis, bukan hanya memenuhi aspek keselamatan secara teknis. Mencakup kebijakan K3, perencanaan, pelaksanaan, pemantauan/evaluasi, serta peningkatan berkelanjutan. Relevan untuk membangun K3 management system pada fasilitas manufaktur MOLINAS. PP ini masih berstatus berlaku
C61: Permen LHK No. 4 Tahun 2021 | D61: Penentuan dokumen/persetujuan lingkungan berdasarkan jenis & skala kegiatan | E61: Menentukan apakah suatu kegiatan wajib memiliki AMDAL, UKL-UPL, atau SPPL berdasarkan jenis usaha, KBLI, lokasi, skala/besaran kegiatan, dan potensi dampaknya. Untuk MOLINAS, regulasi ini penting saat menentukan environmental document requirement untuk fasilitas manufaktur/assembly, termasuk berdasarkan kapasitas dan karakteristik kegiatannya
C62: PP No. 22 tahun 2021 | D62: Mengatur penyelenggaraan perlindungan dan pengelolaan lingkungan hidup, termasuk ketentuan mengenai pengelolaan limbah B3 dan non-B3. | E62: Menjadi dasar pengelolaan aspek lingkungan MOLINAS, terutama pengendalian dampak kegiatan manufaktur, pengelolaan limbah, dan pemenuhan persyaratan lingkungan.
A63: 14 | B63: Kemendag | C63: UU No. 7 Tahun 2014 | D63: Mengatur perdagangan dalam negeri dan luar negeri, termasuk kebijakan perdagangan, pengendalian perdagangan, serta barang yang dilarang atau dibatasi. | E63: Menjadi dasar aspek perdagangan MOLINAS, termasuk distribusi kendaraan/komponen dalam negeri dan pengaturan perdagangan luar negeri yang terkait dengan rantai pasok serta ekspor-impor.
A64: 15 | B64: OJK | C64: POJK pembiayaan & leasing | D64: Mengatur kerangka pengaturan dan pengawasan kegiatan jasa keuangan yang terkait dengan pembiayaan dan/atau perusahaan pembiayaan sesuai ketentuan OJK. | E64: Menjadi enabler pembiayaan konsumen, fleet, dan skema pembiayaan kendaraan listrik sehingga dapat mendukung peningkatan adopsi motor listrik dalam MOLINAS.
C65: Ketentuan pembiayaan konsumen/fleet | D65: Mengatur kegiatan pembiayaan konsumen dan pembiayaan untuk kebutuhan usaha/fleet sesuai ketentuan sektor jasa keuangan. | E65: Mendukung skema pembiayaan pembelian motor listrik oleh individu, perusahaan, fleet, dan institusi dalam rangka memperluas demand MOLINAS.
C66: Green financing | D66: Mendorong pembiayaan berkelanjutan/berwawasan lingkungan sesuai kerangka keuangan berkelanjutan yang berlaku. | E66: Dapat menjadi enabler pembiayaan kendaraan rendah emisi, investasi hijau, dan pengembangan rantai pasok MOLINAS; penerapannya mengikuti kriteria dan ketentuan pembiayaan berkelanjutan.
A67: 16 | B67: Himbara (Bank Mandiri, BRI BNI, BTN, BSI) | C67: Ketentuan perbankan & pembiayaan | D67: Mengatur kegiatan perbankan, pembiayaan, dan layanan keuangan sesuai ketentuan perbankan yang berlaku. | E67: Berpotensi menjadi mitra pembiayaan untuk konsumen, fleet, investasi, modal kerja, dan supply-chain financing dalam ekosistem MOLINAS.
C68: Ketentuan perbankan & pembiayaan | D68: Mengatur kegiatan perbankan dan pembiayaan sesuai ketentuan yang berlaku. | E68: Berpotensi mendukung pembiayaan retail, UMKM, fleet, investasi, dan supply-chain financing untuk pelaku ekosistem MOLINAS.
C69: Ketentuan perbankan & pembiayaan | D69: Mengatur kegiatan perbankan dan pembiayaan sesuai ketentuan yang berlaku. | E69: Berpotensi mendukung corporate financing, investasi, fleet, dan supply-chain financing dalam pengembangan ekosistem MOLINAS.
C70: Ketentuan perbankan & pembiayaan | D70: Mengatur kegiatan perbankan dan pembiayaan sesuai ketentuan yang berlaku. | E70: Berpotensi menjadi mitra pembiayaan konsumen/produk kendaraan listrik sesuai produk dan skema pembiayaan yang tersedia.
C71: Ketentuan perbankan & pembiayaan | D71: Mengatur kegiatan perbankan syariah dan pembiayaan sesuai prinsip serta ketentuan yang berlaku. | E71: Berpotensi mendukung skema pembiayaan kendaraan listrik berbasis syariah bagi konsumen, pelaku usaha, dan rantai pasok MOLINAS.
A72: 17 | B72: BRIN | C72: Riset & teknologi baterai, BMS, charging, keselamatan | D72: Melaksanakan riset dan pengembangan teknologi yang relevan dengan baterai, Battery Management System (BMS), charging, keselamatan, material, dan teknologi kendaraan listrik. | E72: Berperan sebagai research/technology enabler MOLINAS untuk pengembangan dan pengujian teknologi baterai, BMS, charging, material, keselamatan, dan motor listrik.
C73: SNI/riset komponen kelistrikan | D73: Mendukung riset, pengembangan, dan pengujian teknologi/komponen kelistrikan; penetapan SNI berada dalam kerangka standardisasi nasional. | E73: Relevan untuk mendukung pengembangan teknologi dan kesiapan komponen lokal MOLINAS agar memenuhi kebutuhan kinerja, keselamatan, dan standardisasi.
A74: 18 | B74: BSN | C74: SNI kendaraan, baterai & komponen | D74: Mengembangkan dan menetapkan Standar Nasional Indonesia (SNI) sebagai acuan standardisasi nasional sesuai kewenangannya. | E74: Menjadi acuan mutu, keselamatan, kinerja, dan persyaratan teknis kendaraan, baterai, serta komponen dalam ekosistem MOLINAS.
C75: SNI baterai & keselamatan | D75: Mengembangkan dan menetapkan standar nasional terkait mutu, kinerja, dan keselamatan baterai serta komponen terkait. | E75: Mendukung kepastian standar keselamatan dan kinerja baterai dalam MOLINAS serta menjadi referensi bagi produsen dan lembaga penilaian kesesuaian.
C76: SNI kendaraan/rangka, rem, suspensi, dll. | D76: Mengembangkan dan menetapkan standar teknis kendaraan dan komponen untuk mendukung keselamatan, mutu, dan kesesuaian teknis. | E76: Menjadi referensi teknis bagi pengembangan produk motor listrik MOLINAS agar memenuhi persyaratan keselamatan dan kinerja.
A77: 19 | B77: LSPro | C77: Sertifikasi kesesuaian SNI | D77: Melakukan penilaian dan sertifikasi kesesuaian produk terhadap SNI apabila dipersyaratkan dan tercakup dalam ruang lingkup sertifikasinya. | E77: Berperan memastikan produk/komponen MOLINAS memperoleh sertifikasi kesesuaian SNI ketika diwajibkan atau dibutuhkan sesuai skema dan ruang lingkup sertifikasi.
C78: Penilaian/sertifikasi kesesuaian produk terhadap SNI | D78: Melaksanakan penilaian atau sertifikasi kesesuaian produk terhadap SNI sesuai persyaratan dan ruang lingkup lembaga. | E78: Menjadi bagian dari assurance/compliance chain MOLINAS untuk memastikan produk memenuhi standar yang dipersyaratkan sebelum dipasarkan atau digunakan.
A79: 20 | B79: Puslaik Kemhan | C79: UU No. 16/2012; standar/kebijakan kelaikan pertahanan | D79: Mendukung pelaksanaan persyaratan kelaikan dan teknis peralatan/kendaraan yang digunakan untuk kepentingan pertahanan sesuai kewenangannya. | E79: Relevan apabila produk motor listrik MOLINAS digunakan untuk kebutuhan pertahanan, khususnya pemenuhan persyaratan kelaikan dan teknis.
A80: 21 | B80: Grab* | C80: Ketentuan operasional/fleet yang relevan | D80: Mencakup kebutuhan operasional armada dan layanan fleet sesuai model bisnis serta ketentuan yang berlaku. | E80: Berpotensi menjadi anchor demand/fleet user MOLINAS untuk deployment kendaraan listrik dan pengujian kebutuhan charging, baterai, maintenance, dan service level.
A81: 22 | B81: Gojek* | C81: Ketentuan operasional/fleet yang relevan | D81: Mencakup ketentuan operasional armada, keselamatan, layanan, dan kebutuhan fleet sesuai model bisnis dan ketentuan yang berlaku. | E81: Berpotensi menjadi anchor demand/fleet user MOLINAS untuk menguji dan mengembangkan kebutuhan range, utilisasi, charging/swapping, maintenance, TCO, dan after-sales.
A82: 23 | B82: Pos Indonesia | C82: Ketentuan operasional/fleet yang relevan | D82: Mencakup ketentuan dan kebutuhan operasional armada logistik/kurir serta persyaratan penggunaan kendaraan dalam kegiatan layanan. | E82: Berpotensi menjadi fleet user MOLINAS untuk kendaraan logistik/kurir, dengan fokus pada range, payload, charging, uptime, biaya operasi, dan penggantian armada.
A83: 24 | B83: JNE | C83: Ketentuan operasional/fleet yang relevan | D83: Mencakup kebutuhan operasional armada logistik/last-mile sesuai kegiatan usaha dan ketentuan yang berlaku. | E83: Berpotensi menjadi fleet user MOLINAS untuk kebutuhan logistik/last-mile, terutama pengujian range, payload, uptime, charging, maintenance, dan TCO.
A84: 25 | B84: GESITS (Teknologi) | C84: Ketentuan industri/manufaktur, TKDN dan type approval | D84: Mencakup persyaratan industri/manufaktur kendaraan, TKDN, sertifikasi, uji tipe, keselamatan, dan ketentuan produksi yang berlaku. | E84: Berpotensi menjadi OEM/product partner MOLINAS untuk pengembangan, produksi, dan deployment E2W sesuai persyaratan teknis, TKDN, dan standardisasi.
A85: 26 | B85: AESMOLI | C85: Kebijakan/regulasi industri kendaraan listrik | D85: Berperan sebagai asosiasi industri yang merepresentasikan pelaku industri kendaraan listrik dan menyampaikan masukan terkait kebijakan serta pengembangan industri. | E85: Menjadi kanal representasi dan koordinasi industri MOLINAS untuk menyampaikan kebutuhan pelaku usaha, masukan kebijakan, standardisasi, TKDN, serta pengembangan ekosistem kendaraan listrik.
A86: 27 | B86: Mitra terkait* | C86: Regulasi korporasi, investasi, pembiayaan dan partnership yang relevan | D86: Mencakup ketentuan korporasi, investasi, pembiayaan, kemitraan, pengadaan, manufaktur, dan distribusi sesuai jenis kegiatan masing-masing mitra. | E86: Mendukung investasi, JV/partnership, pembiayaan, pengadaan komponen, manufaktur, distribusi, dan pengembangan rantai nilai ekosistem MOLINAS.
A87: 28 | B87: Komdigi | C87: Permenkominfo No. 3/2024 | D87: Mengatur sertifikasi alat dan/atau perangkat telekomunikasi sesuai ruang lingkup peraturan. | E87: Relevan untuk komponen atau fitur kendaraan MOLINAS yang menggunakan perangkat telekomunikasi/radio dan masuk dalam objek sertifikasi, misalnya perangkat konektivitas atau komunikasi.
A88: 29 | B88: IBC | C88: Perpres No. 55 Tahun 2019 tentang Percepatan Program KBLBB untuk Transportasi Jalan | D88: Menetapkan kerangka percepatan pengembangan ekosistem kendaraan bermotor listrik berbasis baterai, termasuk pengembangan industri komponen, baterai, infrastruktur pendukung, penggunaan produk dalam negeri, serta dukungan pemerintah. | E88: Menjadi payung kebijakan utama bagi pengembangan IBC dalam ekosistem baterai dan KBLBB nasional.
C89: Perpres No. 79 Tahun 2023 tentang Perubahan atas Perpres No. 55 Tahun 2019 | D89: Memperkuat dan memperluas ekosistem KBLBB, termasuk penyesuaian ketentuan TKDN dan dukungan pemerintah terhadap percepatan ekosistem kendaraan listrik. | E89: Relevan untuk IBC dalam mendukung pendalaman industri baterai domestik dan integrasi dengan OEM dalam ekosistem MOLINAS.
C90: Permenperin No. 28 Tahun 2023 tentang TKDN KBLBB | D90: Mengatur ketentuan Tingkat Komponen Dalam Negeri pada kendaraan bermotor listrik berbasis baterai dan komponen/aktivitas industri yang mendukung pencapaian TKDN. | E90: Menjadi acuan IBC dalam pengembangan battery cell domestik dan peningkatan local value creation untuk mendukung target TKDN kendaraan listrik.
A91: 30 | B91: Danantara | C91: UU No. 1 Tahun 2025 | D91: Perubahan Ketiga atas UU No. 19 Tahun 2003 tentang BUMN | E91: Menjadi dasar pembentukan dan penguatan kelembagaan Danantara serta mandat pengelolaan dan optimalisasi investasi/aset BUMN. Relevan sebagai landasan keterlibatan Danantara dalam strategic investment dan financing MOLINAS.
C92: PP No. 10 Tahun 2025 jo. PP No. 19 Tahun 2026 | D92: Organisasi dan Tata Kelola BPI Danantara | E92: Mengatur organisasi, tata kelola, serta kewenangan Danantara. Relevan untuk menentukan mekanisme engagement, pengambilan keputusan, dan alignment investasi/pembiayaan yang dapat mendukung MOLINAS.
C93: PP No. 34 Tahun 2025 | D93: Tata Cara Pengelolaan Aset BPI Danantara | E93: Mengatur tata cara pengelolaan aset Danantara. Relevan untuk aspek pengelolaan dan pengembangan investasi/aset yang dapat dikaitkan dengan strategic financing dan pengembangan ekosistem MOLINAS.
C94: UU No. 16 Tahun 2025 | D94: Perubahan Keempat atas UU No. 19 Tahun 2003 tentang BUMN | E94: Memperkuat kerangka kelembagaan dan tata kelola BUMN serta pengaturan terkait fungsi investasi. Relevan sebagai landasan kelembagaan Danantara dalam mendukung agenda investasi strategis, termasuk peluang pengembangan MOLINAS.
A95: 31 | B95: ATMI | C95: UU No. 20 Tahun 2003 | D95: Sistem Pendidikan Nasional | E95: Dasar penyelenggaraan pendidikan nasional. Relevan untuk pengembangan pendidikan vokasi dan SDM pendukung ekosistem MOLINAS.
C96: UU No. 12 Tahun 2012 | D96: Pendidikan Tinggi | E96: Mengatur penyelenggaraan pendidikan tinggi, termasuk pendidikan vokasi. Relevan dengan pengembangan kompetensi SDM teknis untuk MOLINAS.
C97: PP No. 57 Tahun 2021 jo. PP No. 4 Tahun 2022 | D97: Standar Nasional Pendidikan | E97: Mengatur Standar Nasional Pendidikan. Relevan sebagai kerangka standar mutu pendidikan dan pengembangan kompetensi vokasi.
C98: Permendikbudristek No. 53 Tahun 2023 | D98: Penjaminan Mutu Pendidikan Tinggi | E98: Mengatur sistem penjaminan mutu dan standar pendidikan tinggi. Relevan untuk memastikan program pendidikan vokasi yang mendukung MOLINAS memiliki standar mutu.
A99: 32 | B99: Adyawinsa | C99: Permenperin No. 35 Tahun 2025 | D99: Ketentuan dan Tata Cara Sertifikasi TKDN dan BMP | E99: Mengatur penghitungan, verifikasi, sertifikasi, surveilans, dan pengawasan TKDN/BMP. Relevan untuk validasi kandungan lokal komponen dan proses manufaktur Adyawinsa.
C100: Permenperin No. 37 Tahun 2025 | D100: Standar Kegiatan Usaha dan/atau Standar Produk/Jasa pada Perizinan Berusaha Berbasis Risiko Sektor Perindustrian | E100: Mengatur standar kegiatan usaha dan produk/jasa sektor industri. Relevan dengan kesiapan kegiatan manufaktur dan produksi komponen untuk MOLINAS.
...

Sheet USULAN & PERBANDINGAN
A1: No | B1: Kategori | C1: Perpres 55/2019 – Basis Pengaturan | D1: Perpres 79/2023 – Perubahan | E1: Gap / Kebutuhan 2026–2035 | F1: Usulan Penyempurnaan Perpres 2026–2035 | G1: Usulan TKDN 2026–2035 | H1: Prioritas R&D 2026–2035
A2: 1 | B2: Mineral & Bahan Baku | C2: Belum mengatur mineral kritis sebagai bagian eksplisit dari ekosistem KBLBB. Fokus pada percepatan industri, termasuk pengembangan industri komponen dan TKDN. | D2: Tidak terdapat perubahan substansial yang mengintegrasikan upstream mineral dengan ekosistem baterai. | E2: Ketahanan pasok baterai masih bergantung pada rantai mineral–refining–precursor–material aktif. Belum ada pendekatan end-to-end. | F2: Memperluas ekosistem KBLBB sampai upstream bahan baku strategis. Mengintegrasikan roadmap mineral kritis dengan baterai, hilirisasi, traceability, ketahanan pasok, efisiensi penggunaan material dan pengembangan material substitusi. | G2: Target TKDN kendaraan tetap mengikuti tahapan 40% → 60% → 80%, tetapi pendalaman perlu diarahkan ke local value creation upstream. Perlu indikator/milestone lokal untuk refining, precursor dan material aktif, bukan hanya menghitung kandungan pada kendaraan akhir. | H2: 10% dari total portofolio R&D KBLBB diarahkan pada refining, material baterai, precursor, material aktif, efisiensi material dan substitusi mineral kritis.
A3: 2 | B3: Baterai & Teknologi Baterai | C3: Baterai telah menjadi bagian ekosistem KBLBB; industri komponen, TKDN dan R&D didorong; pengelolaan limbah baterai mulai diperhatikan. | D3: Pengaturan diperkuat melalui TKDN, R&D, SPBKLU dan perluasan ekosistem KBLBB. | E3: Belum sepenuhnya menggunakan perspektif battery lifecycle dari bahan baku sampai recycling/second-life. | F3: Mengubah pendekatan dari battery component menjadi battery lifecycle ecosystem. Mencakup cell, module/pack, BMS, thermal management, safety, diagnostics/SOH, second-life, collection, recycling, recovery, traceability dan battery passport. | G3: Mempertahankan trajectory 40% → 60% → 80%, tetapi TKDN harus semakin berbasis komponen kritis. Tahap pendalaman: pack/BMS/thermal management → cell → komponen/material kritis, mengikuti kesiapan teknologi dan industri. | H3: 20% dari portofolio R&D KBLBB untuk battery safety, fast charging, SOH/diagnostics, thermal management, LFP/NMC dan chemistry alternatif, second-life, recycling dan battery passport.
A4: 3 | B4: Powertrain & Komponen Elektrikal | C4: Produksi komponen utama/pendukung, TKDN, R&D dan standardisasi telah didorong. | D4: Ketentuan komponen dan R&D dipertahankan dengan penyesuaian TKDN. | E4: Target TKDN agregat belum otomatis menghasilkan penguasaan teknologi inti seperti motor, inverter, controller dan power electronics. | F4: Memperdalam lokalisasi teknologi inti powertrain, termasuk motor, inverter/controller, BMS, charger, power electronics dan komponen kritis; disertai supplier development dan transfer teknologi. | G4: 40% → 60% → 80% tetap menjadi baseline kendaraan, tetapi perlu sub-target komponen kritis agar pencapaian TKDN tidak hanya berasal dari komponen non-kritis atau assembly. | H4: 20% untuk motor listrik, inverter/controller, semiconductor/power electronics, thermal management, control system dan system efficiency.
A5: 4 | B5: Chassis / Rangka & Komponen Kendaraan | C5: Manufaktur domestik, TKDN, uji tipe dan pengujian berkala telah diatur. | D5: Tidak ada perubahan fundamental pada chassis/komponen. | E5: Lokalisasi relatif lebih memungkinkan, tetapi kemampuan engineering, material dan safety perlu diperdalam. | F5: Memperkuat domestic engineering & supplier capability untuk frame, suspension, steering, braking, wheel, body dan safety component. | G5: Target mengikuti 40% → 60% → 80%, dengan milestone komponen feasible untuk diproduksi domestik. Penilaian diarahkan bukan hanya pada kuantitas kandungan lokal tetapi juga kemampuan desain/manufaktur. | H5: 5% untuk lightweighting, structural engineering, crashworthiness, durability dan advanced material.
A6: 5 | B6: Manufaktur & Perakitan | C6: Pembangunan fasilitas manufaktur domestik, produksi komponen, tahapan manufaktur dan TKDN menjadi instrumen utama. | D6: Perpres 79/2023 memberi ruang CBU dalam rangka investasi/komitmen produksi domestik dan menyesuaikan ketentuan TKDN. | E6: Risiko kebijakan berhenti pada assembly atau investasi awal; perlu transisi menuju manufacturing deepening. | F6: Menjadikan fase CBU sebagai transisi menuju pendalaman manufaktur domestik. Dukungan dikaitkan dengan investasi, produksi, TKDN, supplier localization, transfer teknologi, tenaga kerja, R&D dan ekspor. | G6: 40% → 60% → 80% menjadi minimum trajectory, tetapi pencapaiannya perlu dikaitkan dengan local supplier milestone, kedalaman proses produksi dan ownership teknologi. | H6: 15% untuk design engineering, process engineering, automation, quality system, manufacturing technology dan production digitalization.
A7: 6 | B7: Sertifikasi & Keselamatan Kendaraan | C7: Uji tipe, uji berkala, NIK, laik jalan, garansi dan registrasi menjadi dasar ketentuan teknis kendaraan. | D7: Tidak ada perubahan fundamental pada kerangka sertifikasi, tetapi teknologi EV berkembang jauh lebih cepat. | E7: Kerangka konvensional belum cukup menjawab battery safety, functional safety, cybersecurity, OTA, software dan battery health. | F7: Memperluas assurance framework untuk EV dan software-defined vehicle, termasuk battery safety, functional safety, cybersecurity, OTA/software validation, SOH dan digital vehicle record. | G7: TKDN diarahkan pada alat, sistem dan kemampuan pengujian domestik: test equipment, battery testing, software validation dan certification capability. | H7: 8% untuk testing/certification technology, battery safety, functional safety, cybersecurity, software validation dan interoperability.
A8: 7 | B8: Infrastruktur Pengisian & Ketenagalistrikan | C8: Charging, SPKLU dan peran PLN telah menjadi bagian ekosistem; dukungan tarif dan infrastruktur diatur. | D8: Cakupan diperkuat dengan SPKLU/SPBKLU serta aspek instalasi dan ketenagalistrikan. | E8: Pengaturan masih kuat pada penyediaan fasilitas; kebutuhan berikutnya adalah interoperability, smart charging dan grid integration. | F8: Mengubah charging infrastructure menjadi integrated charging ecosystem: interoperability, roaming/payment, fast & ultrafast charging, load management, smart charging, renewable integration dan V2G. | G8: TKDN difokuskan pada charger, connector, metering, controller, power electronics dan sistem integrasi, dengan target meningkat sesuai kesiapan industri. | H8: 7% untuk smart charging, load management, V2G, grid integration, renewable-powered charging dan charging interoperability.
A9: 8 | B9: Konektivitas & Digital | C9: Belum terdapat kerangka khusus connected vehicle/digital ecosystem. | D9: Belum ada perubahan fundamental yang membentuk digital vehicle ecosystem. | E9: EV semakin menjadi platform digital; data, software, connectivity dan cybersecurity menjadi bagian lifecycle kendaraan. | F9: Menambahkan digital/connected vehicle sebagai bagian formal ekosistem KBLBB, meliputi TCU/IoT, GPS/4G/5G, vehicle data, cybersecurity, OTA, digital vehicle record dan koneksi dengan battery passport. | G9: TKDN diarahkan pada TCU/telematics, software/platform, data services dan digital ecosystem. Pendekatan TKDN perlu mempertimbangkan software dan intangible technology value, bukan hanya physical component. | H9: 5% untuk vehicle data architecture, cybersecurity, OTA, telematics, AI/analytics dan digital records.
A10: 9 | B10: Fiskal, Perdagangan & Pembiayaan | C10: Insentif fiskal/nonfiskal mencakup bea masuk, pajak, PPN/PPnBM, SPKLU, R&D, ekspor, charging dan pembiayaan. | D10: Bantuan pembelian/konversi roda dua dan dukungan CBU/domestik diperkuat dengan persyaratan dan komitmen tertentu. | E10: Insentif masih perlu diarahkan dari market stimulation menjadi industrial capability & technology creation. | F10: Membentuk performance-based incentive framework: dukungan dikaitkan dengan TKDN, investasi, produksi, supplier lokal, tenaga kerja, R&D, ekspor dan kontribusi emisi; termasuk milestone, monitoring dan exit strategy. | G10: Intensitas insentif semakin dikaitkan dengan pencapaian TKDN dan local value creation; semakin dalam lokalisasi dan teknologi domestik, semakin kuat dukungan. | H10: 7% untuk matching fund, applied R&D, technology adoption, commercialization dan industrial research.
A11: 10 | B11: Lingkungan & Ekonomi Sirkular | C11: Pengelolaan limbah baterai melalui pihak berizin dan aspek lingkungan menjadi bagian program KBLBB. | D11: Tidak ada perubahan fundamental. | E11: Pendekatan masih lebih dekat ke waste management dibanding lifecycle/circular economy. | F11: Membangun battery circular economy framework, termasuk producer responsibility, collection, traceability, diagnosis, safe dismantling, second-life, recycling, recovery dan material recovery. | G11: TKDN dikembangkan pada collection, diagnostics, dismantling, recycling dan recovery, sehingga nilai tambah tidak berhenti pada kendaraan baru. | H11: 3% untuk second-life, recycling efficiency, safe dismantling, material recovery dan circular design.
A12: 11 | B12: Pertahanan & Strategic Use Case | C12: Belum secara spesifik menempatkan KBLBB sebagai strategic/defense use case. | D12: Tidak terdapat perubahan fundamental terkait strategic use case. | E12: Kebutuhan kendaraan institusional/pertahanan berbeda dari kendaraan komersial dan dapat menjadi anchor demand teknologi domestik. | F12: Membuka strategic/institutional pathway dalam ekosistem KBLBB, termasuk procurement, spesifikasi khusus, security requirement, lifecycle support dan keterlibatan industri strategis. | G12: TKDN diarahkan pada kemandirian platform dan komponen strategis, bukan sekadar memenuhi persentase kendaraan. Procurement pemerintah dapat menjadi anchor demand. | H12: 3% untuk ruggedized EV, mission-specific battery/powertrain, secure communication, energy resilience dan defense-grade testing.
A13: 12 | B13: Program Strategis Nasional & Kelembagaan Lintas Sektor | C13: Sudah terdapat mekanisme koordinasi K/L, rencana aksi dan pengawasan percepatan KBLBB. | D13: Governance diperkuat untuk mendukung perluasan ekosistem. | E13: Koordinasi perlu naik menjadi ecosystem governance dengan single data, KPI, monitoring dan periodic review. | F13: Membangun National EV Ecosystem Governance: single data, KPI dashboard, roadmap lintas K/L, funding alignment, monitoring-evaluation dan periodic policy review. | G13: Target agregat 40% → 60% → 80% diterjemahkan menjadi milestone per rantai nilai, sehingga pemerintah dapat memonitor kedalaman TKDN, bukan hanya angka agregat kendaraan. | H13: 10% untuk national R&D portfolio, shared testing facility, technology readiness monitoring dan integrasi riset lintas kategori.

Sheet DATABASE BERITA
A1: No | B1: Tanggal Berita | C1: Negara | D1: Perusahaan / Brand | E1: Pilar Ekosistem | F1: Area Fokus | G1: Ringkasan Berita | H1: Angka & Insight Kunci | I1: Media / Sumber | J1: Link Berita | K1: Jenis Berita
A2: 1 | B2: 46274 | C2: Indonesia | D2: BKPM / Pemerintah | E2: ENABLERS | F2: Charging / Swapping | G2: BKPM melonggarkan kebijakan investasi SPKLU karena ketersediaan charging station belum mampu mengimbangi pertumbuhan permintaan EV. Pemerintah mengubah pendekatan investasi sehingga minimum investasi Rp10 miliar dapat digunakan untuk membangun beberapa titik SPKLU dalam cakupan satu provinsi atau kabupaten, sekaligus mendorong keterlibatan BUMN, Danantara, dan swasta. | H2: Minimum investasi Rp10 miliar sebelumnya dikaitkan dengan satu titik; kini dapat mencakup beberapa titik dalam satu provinsi/kabupaten. Biaya satu mesin SPKLU sekitar Rp200–300 juta. Pemerintah juga mendorong interoperabilitas agar satu charging station dapat melayani berbagai merek EV. | I2: ANTARA | J2: https://www.antaranews.com/berita/5732237/bkpm-longgarkan-investasi-spklu-guna-kejar-pertumbuhan-ev | K2: Lokal
A3: 2 | B3: 46273 | C3: Indonesia | D3: IBC / CATL | E3: VALUE CHAIN (HULU–MIDSTREAM–HILIR) | F3: HULU — Battery & Components | G3: Produksi baterai EV dari fasilitas IBC–CATL di Karawang saat ini lebih banyak diarahkan untuk pasar ekspor, sementara penyerapan domestik masih relatif kecil. IBC telah membahas calon offtaker lokal, termasuk kerja sama dengan PT Len Industri dalam program MoLiNas. Kondisi ini menunjukkan tantangan ekosistem bergeser dari pembangunan kapasitas baterai menuju penguatan domestic absorption dan lokalisasi. | H3: Kapasitas awal pabrik 6,9 GWh/tahun dan direncanakan meningkat menjadi sekitar 15 GWh. Pasar domestik masih minoritas; IBC telah berdiskusi dengan PT Len terkait MoLiNas. Produksi awal didominasi LFP, sementara NMC diharapkan meningkat setelah fasilitas material baterai domestik beroperasi. | I3: Bisnis.com | J3: https://ekonomi.bisnis.com/read/20260908/44/2002459/ibc-ungkap-baterai-ev-pabrik-karawang-lebih-banyak-untuk-pasar-ekspor | K3: MoLiNas
A4: 3 | B4: 46270 | C4: Indonesia | D4: Pemerintah / MoLiNas | E4: REGULATORY & POLICY | F4: Regulasi, Kebijakan & Insentif | G4: Insentif motor listrik belum resmi berlaku. September masih menjadi target implementasi, sementara PMK dan dasar hukum pelaksana masih dalam proses. | H4: Rp3 juta/unit; kerangka anggaran Rp3 triliun; hingga 1 juta unit. Wacana awal 2026 Rp5 juta/unit. Rp7 juta merupakan skema historis 2023–2024. | I4: ITERA | J4: Artikel ITERA – Update 5 September 2026 | K4: MoLiNas
A5: 4 | B5: 46270 | C5: Indonesia | D5: DPR RI / BYD | E5: REGULATORY & POLICY | F5: TKDN & Sertifikasi | G5: Komisi XII DPR menekankan peningkatan TKDN BYD harus disertai transfer teknologi kepada pekerja lokal. Fokus local content diperluas dari persentase komponen ke peningkatan kapabilitas SDM dan knowledge transfer. | H5: Kunjungan spesifik Komisi XII ke pabrik BYD Subang pada 4 Sep 2026; transfer teknologi kepada pekerja lokal ditekankan. | Issue: Tanpa transfer knowledge, local assembly berisiko menghasilkan ketergantungan teknologi. | Local content: Local content sebaiknya diukur bersama capability building, bukan hanya persentase pembelian domestik. | Manufacturing: Mendorong training, engineering capability, technical management dan knowledge transfer di fasilitas manufaktur. | I5: DPR RI | J5: https://jdih.dpr.go.id/berita/detail/id/68788/t/Peningkatan%2BTKDN%2BBYD%2BHarus%2BDiikuti%2BTransfer%2BTeknologi%2Bkepada%2BPekerja%2BLokal | K5: Lokal
A6: 5 | B6: 46270 | C6: Indonesia | D6: BYD | E6: REGULATORY & POLICY | F6: TKDN & Sertifikasi | G6: BYD mengoperasikan pabrik Subang dengan proses manufaktur yang lebih lengkap dan menggandeng ekosistem komponen pendukung untuk mengejar TKDN. Pendalaman manufaktur mencakup proses stamping, welding dan painting serta pengembangan supplier komponen lokal. | H6: Target TKDN 60% pada 2027; proses disebut mencakup stamping, welding, painting. | Issue: Kedalaman localization harus dilihat dari proses dan supplier, bukan hanya lokasi assembly. | Local content: Menunjukkan bagaimana OEM dapat mengejar TKDN melalui domestic process + component sourcing. | Manufacturing: Membuka peluang tier-1/tier-2 supplier dan proses manufaktur domestik. | I6: OtoDream | J6: https://www.otodream.com/ev/35778-byd-optimistis-tkdn-mobil-produksi-subang-capai-60-persen-pada-2027 | K6: Lokal
A7: 6 | B7: 46270 | C7: Indonesia | D7: DPR RI / BYD | E7: VALUE CHAIN (HULU–MIDSTREAM–HILIR) | F7: MIDSTREAM — OEM / Manufacturing | G7: DPR mendorong BYD memperluas penggunaan tenaga kerja lokal hingga posisi administrasi dan manajemen, bukan hanya operator/support. Local benefit dari investasi EV dibahas sebagai workforce localization, bukan hanya factory output. | H7: Kunjungan Komisi XII pada 4 Sep 2026; dorongan agar tenaga kerja lokal masuk hingga management. | Issue: Manfaat investasi dapat dangkal bila workforce localization hanya di level operasional. | Local content: Memperluas definisi domestic value creation ke tenaga kerja dan managerial capability. | Manufacturing: Mendorong pembangunan local engineering, supervisory dan management capability. | I7: DPR RI / E-Media | J7: https://emedia.dpr.go.id/news/2026/09/05/rokhmat-ardiyan-dorong-byd-libatkan-tenaga-kerja-lokal-hingga-manajemen | K7: Lokal
A8: 7 | B8: 46270 | C8: Indonesia | D8: KLH / Pemerintah RI | E8: REGULATORY & POLICY | F8: Regulasi, Kebijakan & Insentif | G8: KLH menargetkan ekosistem pengelolaan limbah baterai EV selesai pada 2027, dimulai dari penguatan regulasi pada 2026. Regulatory groundwork dipercepat sebelum volume baterai bekas meningkat. | H8: Regulasi 2026; ecosystem target 2027. | Issue: Perlu pembagian peran produsen, collector, recycler dan regulator. | Local content: Menciptakan basis regulatory certainty untuk investasi battery recycling dan second-life. | Manufacturing: Memberi sinyal pasar untuk membangun fasilitas recycling dan reverse logistics domestik. | I8: Katadata | J8: https://katadata.co.id/berita/nasional/6a9b715510f06/klh-targetkan-ekosistem-pengelolaan-limbah-baterai-ev-rampung-tahun-depan | K8: Lokal
A9: 8 | B9: 46270 | C9: Indonesia | D9: CATL / EV Industry | E9: VALUE CHAIN (HULU–MIDSTREAM–HILIR) | F9: MIDSTREAM — Quality Assurance | G9: CATL memperingatkan risiko kegagalan baterai di tengah percepatan peluncuran model EV dan siklus pengujian yang makin pendek. Isu manufacturing ecosystem tidak hanya capacity dan TKDN, tetapi juga quality validation, safety dan engineering discipline. | H9: Sekitar 600 model EV disebut telah diluncurkan sepanjang 2026; harga sel LFP dilaporkan turun di bawah 0,35 yuan/Wh. | Issue: Tekanan cost dan speed-to-market dapat memendekkan validation cycle dan meningkatkan quality risk. | Local content: Local manufacturing perlu membangun capability kualitas setara standar global, bukan sekadar memenuhi TKDN. | Manufacturing: Menekankan battery testing, validation, thermal/safety engineering, supplier quality dan traceability. | I9: ANTARA | J9: https://m.antaranews.com/amp/berita/5727535/catl-wanti-wanti-soal-baterai-gagal-di-tengah-banjir-produksi-ev | K9: Lokal
A10: 9 | B10: 46270 | C10: India | D10: Ola Electric Mobility (Hasil Rapat Dewan: Fundraise Rp1.500 Crore) | E10: ENABLERS | F10: Financing & Support | G10: Hasil rapat dewan Ola Electric pada 5 September 2026 menyetujui penggalangan dana hingga ₹1.500 crore melalui penerbitan saham ekuitas dan/atau efek yang dapat dikonversi menjadi ekuitas. Dewan juga mencatat pengunduran diri COO Hyun Shik Park efektif 5 September 2026 dan menyetujui perpanjangan masa jabatan dua Direktur Independen, dengan persetujuan pemegang saham dijadwalkan dalam RUPS 30 September 2026. | H10: Fundraise disetujui: hingga ₹1.500 crore | COO Hyun Shik Park mundur efektif 5 Sep 2026 | Modal saham resmi dinaikkan menjadi ₹8.721,87 crore | RUPS: 30 Sep 2026 | I10: Autocar Professional | J10: https://www.autocarpro.in/news/ola-electric-approves-rs-1500-crore-fundraise-as-coo-hyun-shik-park-resigns-134555 | K10: Global
A11: 10 | B11: 46270 | C11: India | D11: TVS, Bajaj, Ather, Hero Vida, Ola & lainnya (Data Lengkap Penjualan Agustus 2026) | E11: ENABLERS | F11: Financing & Support | G11: Penjualan retail E2W India pada Agustus 2026 mencapai 182.936 unit, naik 67% YoY namun turun 11% MoM dari rekor Juli. TVS memimpin, diikuti Bajaj, Ather, dan Hero Vida; empat pemain teratas menyumbang sekitar 75% penjualan bulan tersebut. | H11: Total Agustus: 182.936 unit | +67% YoY | -11% MoM | TVS 48.873 | Bajaj 41.019 | Ather 28.708 | Hero Vida 18.978 | Top 4: 137.578 unit / 75% | I11: Autocar Professional | J11: https://www.autocarpro.in/analysis/electric-2w-sales-grow-67-percent-in-august-but-down-11-percent-on-record-july-retails-134423 | K11: Global
A12: 11 | B12: 46270 | C12: India | D12: Ola Electric Mobility (Rencana Penggalangan Dana) | E12: VALUE CHAIN (HULU–MIDSTREAM–HILIR) | F12: HILIR — Sales / Demand | G12: Dewan direksi Ola Electric dijadwalkan menggelar rapat pada 5 September 2026 untuk membahas dan menyetujui proposal penggalangan dana baru melalui penerbitan saham ekuitas atau instrumen efek lain yang layak (private placement, QIP, ataupun rights/preferential issue), hanya tiga bulan setelah perusahaan meraih Rp780 crore lewat QIP sebelumnya. Rencana ini muncul di tengah tekanan berlapis: pangsa pasar yang terus tergerus, keluhan konsumen yang menumpuk, serta harga saham yang telah anjlok ~82% dari puncaknya. Hasil rapat dewan (nilai, instrumen, dan struktur pendanaan final) belum diumumkan per saat entri ini ditulis. | H12: Fundraise sebelumnya: Rp780 crore (QIP, 3 bulan lalu) | Saham turun ~3-4% dalam beberapa sesi jelang rapat | Insentif PLI-Auto FY27 diterima: Rs 95,81 crore (lihat entri No.3) | Status: rapat dewan berlangsung 5 Sep 2026, hasil belum diumumkan | I12: Entrackr / BusinessToday / Zeebiz | J12: https://entrackr.com/news/ola-electric-to-consider-another-fundraise-amid-market-share-pressure-12486838 | K12: Global
A13: 12 | B13: 46269 | C13: Indonesia | D13: KLH / Pemerintah | E13: VALUE CHAIN (HULU–MIDSTREAM–HILIR) | F13: HILIR — Recycling / Circularity | G13: KLH membangun ekosistem pengelolaan limbah baterai kendaraan listrik untuk mengantisipasi peningkatan baterai bekas serta memastikan pengelolaannya dapat dilakukan secara aman dan berkelanjutan. | H13: Umur baterai sekitar 5–8 tahun; puncak timbulan baterai bekas diperkirakan sekitar 2040 apabila penggunaan EV meningkat masif. | I13: ANTARA | J13: https://www.antaranews.com/berita/5726439/klh-bangun-ekosistem-pengelolaan-limbah-baterai-kendaraan-listrik | K13: Lokal
... A93: 92 | B93: 45827 | C93: Indonesia | D93: Pemerintah RI | E93: REGULATORY & POLICY | F93: TKDN & Sertifikasi | G93: Regulasi PPN kendaraan listrik berbasis baterai mensyaratkan minimum TKDN untuk kendaraan yang memperoleh fasilitas. Insentif fiskal dikaitkan dengan persyaratan kandungan lokal, sehingga policy support diarahkan sekaligus untuk industrial development. | H93: Minimum TKDN 40% untuk kendaraan listrik tertentu yang memperoleh fasilitas PPN DTP. | Issue: Insentif tanpa localization dapat meningkatkan demand tetapi tidak otomatis memperdalam domestic value added. | Local content: TKDN menjadi gate untuk memperoleh manfaat fiskal tertentu. | Manufacturing: Mendorong OEM meningkatkan local sourcing untuk mempertahankan eligibility insentif. | I93: Direktorat Jenderal Pajak | J93: https://www.pajak.go.id/id/peraturan/pajak-pertambahan-nilai-atas-penyerahan-kendaraan-bermotor-listrik-berbasis-baterai-1 | K93: Lokal
A94: 93 | C94: Negara | D94: Perusahaan / Brand | E94: Pilar Ekosistem | F94: Area Fokus | G94: Ringkasan Berita | H94: Angka & Insight Kunci | I94: Media / Sumber | J94: Link Berita | K94: Global
A95: 94 | C95: Indonesia–Malaysia | D95: Baterai Nusantara / NBRI / BRIN | E95: VALUE CHAIN (HULU–MIDSTREAM–HILIR) | F95: HULU — Battery & Components | G95: Indonesia dan Malaysia mengembangkan Baterai Nusantara untuk membangun ekosistem baterai ASEAN yang lebih mandiri. BRIN/NBRI terlibat melalui expertise riset dan pengembangan material baterai. | H95: International Battery Summit 26–28 Agu 2026; Indonesia berpotensi berkontribusi pada material/katoda, sementara Malaysia memiliki fasilitas pilot untuk produksi sel baterai. | I95: ANTARA | J95: https://m.antaranews.com/amp/berita/5711873/baterai-nusantara-dorong-kemandirian-ekosistem-baterai-di-asean | K95: Global
A96: 95 | C96: Indonesia | D96: Kementerian Perindustrian | E96: REGULATORY & POLICY | F96: TKDN & Sertifikasi | G96: Kemenperin menerbitkan Permenperin No. 35 Tahun 2026 mengenai ketentuan dan tata cara sertifikasi TKDN serta Bobot Manfaat Perusahaan (BMP). Regulasi baru ini memperbarui framework administratif sertifikasi dan penghitungan TKDN yang menjadi fondasi implementasi local-content policy. | H96: Permenperin No. 35 Tahun 2026; berlaku sebagai framework sertifikasi TKDN dan BMP. | Issue: Perusahaan perlu memastikan data, komponen utama dan proses produksi terdokumentasi sesuai metodologi sertifikasi. | Local content: Relevan sebagai regulatory enabler untuk memastikan klaim TKDN dapat diverifikasi dan menjadi dasar kebijakan industri. | Manufacturing: Memperkuat governance data, traceability komponen dan kesiapan audit manufaktur. | I96: Kemenperin – Ditjen IKMA | J96: https://ikm.kemenperin.go.id/tingkat-komponen-dalam-negeri-tkdn | K96: Lokal
A97: 96 | C97: Indonesia | D97: Kementerian Perindustrian – Ditjen ILMATE | E97: REGULATORY & POLICY | F97: TKDN & Sertifikasi | G97: Ditjen ILMATE menetapkan perubahan rincian komponen utama barang sektor industri logam, mesin, alat transportasi dan elektronika untuk penghitungan TKDN. Ini penting untuk manufacturing karena metodologi TKDN bertumpu pada rincian komponen utama dan klasifikasi sektor. | H97: Perdirjen ILMATE No. 2 Tahun 2026; perubahan atas Perdirjen ILMATE No. 6 Tahun 2025. | Issue: Perubahan rincian komponen dapat memengaruhi bagaimana kontribusi komponen domestik dihitung. | Local content: Membuat hubungan antara local sourcing dan perhitungan TKDN lebih konkret di level komponen. | Manufacturing: Relevan bagi OEM dan supplier untuk mapping BOM, domestic component sourcing dan dokumentasi. | I97: Kemenperin – Ditjen ILMATE | J97: https://ilmate.kemenperin.go.id/pelayanan-publik/peraturan/00ec53c4682d36f5c4359f4ae7bd7ba1?type=repository | K97: Lokal
A98: 97 | C98: Indonesia | D98: Pemerintah RI | E98: REGULATORY & POLICY | F98: TKDN & Sertifikasi | G98: Perpres 79/2023 menjadi baseline kebijakan TKDN KBLBB dan memperkuat arah peningkatan kandungan dalam negeri. Jadwal TKDN ditetapkan bertahap dan menjadi basis kebijakan insentif serta pengembangan industri. | H98: E2W/E3W: minimum 40% hingga 2026; 60% 2027–2029; 80% mulai 2030. | Issue: Pelaku industri harus meningkatkan domestic value creation, bukan sekadar perakitan. | Local content: Ada trajectory yang jelas menuju 80% TKDN untuk roda dua/tiga. | Manufacturing: Memerlukan supplier localization, komponen lokal, battery components dan proses produksi domestik. | I98: BPK – Database Peraturan | J98: https://peraturan.bpk.go.id/Details/273447/perpres-no-79-tahun-2023 | K98: MoLiNas
A99: 98 | C99: India | D99: Ather Energy (Inovasi Produk) | E99: VALUE CHAIN (HULU–MIDSTREAM–HILIR) | F99: HILIR — Sales / Demand | G99: Pada Community Day ke-4, Ather Energy memperkenalkan empat inovasi sekaligus yang mencakup produk, baterai, charging, dan kesehatan kendaraan: skuter Konarc, baterai Bedrock generasi kelima, AtherNode (solusi charging komunitas untuk apartemen), serta Ather True Health untuk penilaian kesehatan baterai/kendaraan dan nilai jual kembali (resale value). | H99: 4 inovasi diluncurkan sekaligus | >4.600 peserta Community Day | Fokus: keamanan baterai, akses charging, kesehatan kendaraan & resale value | I99: Energetica India | J99: https://www.energetica-india.net/news/ather-energy-unveils-four-new-ev-innovations-at-fourth-community-day- | K99: Global
A100: 99 | C100: India | D100: Ather Energy (Kapasitas Produksi) | E100: ENABLERS | F100: Technology, Data & Digital | G100: Ather menghadapi permintaan yang jauh melampaui kapasitas produksinya. CEO Tarun Mehta menyebut permintaan bulanan sudah menembus 50.000 unit, sementara kapasitas produksi saat ini baru sekitar 35.000 unit/bulan — menjadikan ekspansi kapasitas manufaktur sebagai penghambat utama pertumbuhan dalam beberapa kuartal ke depan. | H100: Permintaan: >50.000 unit/bulan | Kapasitas saat ini: \~35.000 unit/bulan | Estimasi waktu mengejar ketertinggalan kapasitas: 3-4 kuartal | I100: Business Standard | J100: https://www.business-standard.com/amp/industry/auto/ather-demand-outstrip-supply-konarc-scooter-tarun-mehta-126083000232_1.html | K100: Global
A101: 100 | C101: Singapura | D101: Kilats / Charged Asia (ekspansi ke Indonesia) | E101: VALUE CHAIN (HULU–MIDSTREAM–HILIR) | F101: MIDSTREAM — Production / Supply | G101: [Temuan tambahan di luar 6 peer inti — Singapura bukan bagian kriteria peer, namun relevan karena ekspansinya langsung menyasar pasar Indonesia] Perusahaan motor listrik asal Singapura menghadapi adopsi domestik yang masih rendah dan mengalihkan pertumbuhan ke Asia Tenggara. Kilats telah menyewakan hampir 700 motor listrik ke Grab di Bali dan Bandung dengan dukungan 44 stasiun swap baterai; Charged Asia telah men-deploy lebih dari 5.000 unit di Indonesia dan menargetkan lebih dari 300.000 unit se-kawasan dalam beberapa tahun ke depan. | H101: E2W di jalan Singapura: 433 unit (per Jul 2026) | Kilats: \~700 unit ke Grab + 44 swap station (Bali/Bandung) | Charged Asia: >5.000 unit di Indonesia, target >300.000 unit regional | I101: Channel NewsAsia | J101: https://www.channelnewsasia.com/singapore/electric-motorbike-companies-singapore-overseas-6347736 | K101: Global
A102: 101 | C102: India | D102: Ather Energy – Konarc | E102: VALUE CHAIN (HULU–MIDSTREAM–HILIR) | F102: HILIR — Sales / Demand | G102: Ather meluncurkan skuter listrik Konarc untuk memperluas penetrasi ke segmen mass-market. Konarc menggunakan platform EL baru dan tersedia dalam enam varian dengan harga mulai ₹99.999 serta range hingga 200 km IDC. | H102: Harga mulai: ₹99.999 | 6 varian | Range hingga 200 km IDC | Platform: EL | Target: memperluas addressable market Ather | I102: Economic Times | J102: https://www.economictimes.indiatimes.com/industry/renewables/ather-launches-konarc-electric-scooter-at-99999-with-200-km-range-10-year-battery-warranty/articleshow/133607676.cms | K102: Global
A103: 102 | C103: China | D103: Luyuan Group | E103: VALUE CHAIN (HULU–MIDSTREAM–HILIR) | F103: HILIR — Sales / Demand | G103: Luyuan memperluas bisnis luar negeri ketika pasar domestik China semakin didorong replacement demand. Perusahaan menekankan bahwa kompetisi ekspor E2W akan makin ditentukan teknologi, brand, compliance, dan local operations—bukan sekadar harga murah. | H103: ~80% permintaan domestik China berasal dari replacement tahun ini | Penjualan luar negeri H1 2026 +~40% YoY | >80 negara/wilayah | 6 innovation centers global | I103: China Daily / eZhejiang | J103: https://www.ezhejiang.gov.cn/jinhua/2026-08/31/c_1209788.htm | K103: Global
A104: 103 | C104: India | D104: Bajaj Auto (Chetak) | E104: VALUE CHAIN (HULU–MIDSTREAM–HILIR) | F104: HILIR — Sales / Demand | G104: Bajaj Auto resmi menjadi produsen EV kedua di India (setelah TVS) yang menembus penjualan 3 lakh (300.000) unit dalam satu tahun kalender, berkat performa kuat Chetak. Berdasarkan data registrasi Vahan, Bajaj mengirimkan 3,02 lakh unit sepanjang Januari-Agustus 2026, tumbuh 68% dibanding periode sama tahun lalu. TVS tetap unggul di posisi puncak dengan 3,53 lakh unit, sementara Ather di posisi ketiga dengan 2,27 lakh unit dan diproyeksi menembus 3 lakh unit sekitar November 2026 didorong peluncuran model mass-market Konarc. | H104: Bajaj: 3,02 lakh unit (Jan-Agu 2026), +68% YoY | TVS (pemimpin pasar): 3,53 lakh unit | Ather: 2,27 lakh unit | Pangsa pasar: Bajaj 22%, Ather 17%, TVS 26% | Proyeksi total Bajaj akhir tahun: 4,25-4,50 lakh unit | I104: Autocar India | J104: https://www.autocarindia.com/bike-news/bajaj-becomes-second-indian-ev-maker-to-cross-3-lakh-sales-this-year-440612 | K104: Global
A105: 104 | C105: Vietnam | D105: Ekosistem motor listrik Vietnam | E105: VALUE CHAIN (HULU–MIDSTREAM–HILIR) | F105: HILIR — Sales / Demand | G105: Pasar motor listrik Vietnam tumbuh sangat cepat pada tujuh bulan pertama 2026. Penjualan mencapai 513.742 unit, naik 97,2% YoY, dan pangsanya meningkat menjadi sekitar 27,6% dari total pasar roda dua. | H105: Penjualan E2W 7M 2026: 513.742 unit | +97,2% YoY | Pangsa: 27,6% | Total pasar 2W: ~1,8 juta unit | Pertumbuhan pasar total: +19,6% | I105: VnExpress | J105: https://vnexpress.net/tieu-thu-xe-may-dien-tai-viet-nam-tiep-tuc-tang-5114587.html | K105: Global
... A131: 130 | C131: Indonesia | D131: Neta Auto Indonesia (mobil listrik, konteks ekosistem) | E131: BERJUANG | F131: Manufaktur & Supply Chain | G131: Meski bukan roda-2, kasus ini relevan sebagai konteks ekosistem EV Indonesia: pabrik mobil listrik Neta asal China di Indonesia diterpa isu pailit menyusul kesulitan finansial induk perusahaannya di China, memaksa unit lokal bermitra dengan Maersk untuk menjamin ketersediaan suku cadang guna menenangkan pasar. | H131: Isu pailit induk usaha di China | Mitigasi: kerja sama logistik suku cadang dengan Maersk | I131: Media24 | J131: https://www.media24.id/auto-tekno/681482533/diterpa-isu-pailit-pabrik-mobil-listrik-asal-china-neta-bertaruh-pada-suku-cadang-di-pasar-otomotif-indonesia | K131: Lokal

Sheet PIC Contacts
A1: MOLINAS PIC CONTACTS
A4: No. | B4: Organization | C4: Contact Person | D4: Position | E4: Phone / Mobile | F4: Email | G4: Address / Notes
A5: 1 | B5: PT Adyawinsa Stamping Industries | C5: Mateus Suwarno | D5: Managing Director | E5: 0812 1055 776 | F5: mateus@adyawinsa.com | G5: Jl. Surotokunto No.109, Karawang, Jawa Barat
A6: 2 | B6: PT Adyawinsa Plastics Industry | C6: Ardiyansyah | D6: PPIC & Production Director | E6: +62 815 9653613 | F6: ardiyansyah.laode@adyawinsa.com | G6: Jl. Angsana Raya Blok L6 No. 1, Delta Silicon I, Lippo Cikarang, Kab. Bekasi, Jawa Barat 17530
A7: 3 | B7: PT ATMI IGI Center / Politeknik ATMI Surakarta | C7: Yustinus Wahyo Nursanto | D7: ATMI IGI Director | E7: +62 815 7976 727; +62 811 2636 681 | F7: wahyu@atmi.co.id | G7: Jl. Adisucipto / Jl. Mojo No. 1, Karangasem, Laweyan, Surakarta 57145
A8: 4 | B8: PT Adyawinsa Electrical and Power | C8: Praditya Sih Ardihantoro | D8: Director | E8: +62 822 8222 7866 | F8: praditya.ardihantoro@adyawinsa.com | G8: Jl. Industri Selatan Blok II No. 4, Kawasan Industri Jababeka II, Desa Pasir Sari, Cikarang Selatan, Bekasi, Jawa Barat 17550
A9: 5 | B9: PT Industri Baterai Indonesia (IBC) | C9: Niko Chandra | D9: Director of Business Development | E9: +62 812 1090 867 | F9: niko.chandra@indonesiabatterycorp.com | G9: PT Industri Baterai Indonesia; Menara Mandiri II Lt. 3A, Jl. Jenderal Sudirman Kav. 54-55, Jakarta 12190
A10: 6 | B10: PT Tri Centrum Fortuna | C10: FX. Kuncara Agus Prabawa | D10: Operational Director | E10: +62 815 1835 132 | F10: kuncara@tricentrumfortuna.com | G10: Head Office & Factory: Jl. Mitra Raya II No. 7-8, Parungmulya, Kec. Ciampel, Karawang, Jawa Barat 41363
A11: 7 | B11: PT Pindad | C11: Ujang Sakiman | D11: General Manager, Kendaraan Multifungsi Nasional | E11: P: +62 22 7312073 ext. 2393; M: +62 819 3134 2510 | F11: ujangsakiman@pindad.com | G11: Jl. Jend. Gatot Subroto No. 517, Bandung 40284, Indonesia
A12: 8 | B12: Asosiasi Perusahaan Pembiayaan Indonesia (APPI) | C12: Sri Haryati | D12: Deputy Director | E12: +62 816 1161 111; +62 21 2982 0190 | F12: sharyati@ifsa.or.id | G12: Kota Kasablanka (EightyEight@Kasablanka), Tower A Lantai 7 Unit D, Jl. Casablanca Kavling 88, Jakarta 12870
A13: 9 | B13: University of California, Davis – Institute of Transportation Studies | C13: Ridhi Palia | D13: Research Associate, India ZEV Research Centre | E13: +91 84476 14701 | F13: rpalia@ucdavis.edu | G13: https://its.ucdavis.edu/
A14: 10 | B14: PT Indomobil Finance Indonesia | C14: Nono Marsono | D14: 2 Wheels Division Head | E14: +62 812 1610 5000; +62 21 2918 5400 ext. 15400 | F14: nono_m@indomobilfinance.com | G14: Indomobil Tower Lt. 9, Jl. MT. Haryono Kav. 11, Jakarta 13330
